Workbook
Name L_DATA: 'Lançamentos'!$B$2:$B$20001
Name L_TIPO: 'Lançamentos'!$C$2:$C$20001
Name L_DESC: 'Lançamentos'!$D$2:$D$20001
Name L_VALOR: 'Lançamentos'!$E$2:$E$20001
Name L_CAT: 'Lançamentos'!$F$2:$F$20001
Name L_CONTA: 'Lançamentos'!$G$2:$G$20001
Name L_DEST: 'Lançamentos'!$H$2:$H$20001
Name L_TIT: 'Lançamentos'!$I$2:$I$20001
Name L_STATUS: 'Lançamentos'!$J$2:$J$20001
Name L_CICLO: 'Lançamentos'!$P$2:$P$20001
Name L_EXCL: 'Lançamentos'!$T$2:$T$20001
Name F_ANO: '_Calc'!$B$2
Name F_INI: '_Calc'!$B$4
Name F_FIM: '_Calc'!$B$5
Name F_INI_ANT: '_Calc'!$B$6
Name F_FIM_ANT: '_Calc'!$B$7
Name F_CONTA_SEL: '_Calc'!$B$8
Name F_CONTA: '_Calc'!$B$9
Name F_TIT: '_Calc'!$B$10
Name HOJE: '_Calc'!$B$11
Name F_TIT_SEL: '_Calc'!$B$12

Sheet Dashboard
B2: Orange Finance | I2: =INDEX('_Listas'!$B$2:$B$13,_Calc!$B$3)&" de "&_Calc!$B$2
B3: ="Dashboard · "&'Metadados'!$B$5
B5: ANO | D5: MÊS | F5: CONTA | H5: Escolha ano, mês e conta: todo o painel se atualiza. Transferências entre contas não entram em receitas e despesas.
B6: =YEAR(TODAY()) | D6: =INDEX('_Listas'!$B$2:$B$13,MONTH(TODAY())) | F6: Todas
B9: RECEITAS DO MÊS | E9: DESPESAS DO MÊS | H9: RESULTADO DO MÊS | K9: TAXA DE POUPANÇA
B10: =_Calc!$E$2 | E10: =_Calc!$E$3 | H10: =_Calc!$E$2-_Calc!$E$3 | K10: =IF(_Calc!$E$2>0,(_Calc!$E$2-_Calc!$E$3)/_Calc!$E$2,0)
B12: =IF(_Calc!$E$4>0,IF(_Calc!$E$2>=_Calc!$E$4,"▲ ","▼ ")&TEXT(ABS(_Calc!$E$2/_Calc!$E$4-1),"0%")&" vs mês anterior","Sem dados no mês anterior") | E12: =IF(_Calc!$E$5>0,IF(_Calc!$E$3>=_Calc!$E$5,"▲ ","▼ ")&TEXT(ABS(_Calc!$E$3/_Calc!$E$5-1),"0%")&" vs mês anterior","Sem dados no mês anterior") | H12: =IF(H10>=0,"Sobrou neste mês","Faltou neste mês") | K12: do que entrou no mês
B14: SALDO EM CONTAS (HOJE) | E14: DÍVIDA EM CARTÕES (HOJE) | H14: A PAGAR NO MÊS | K14: MAIOR CATEGORIA
B15: =_Calc!$E$8 | E15: =_Calc!$E$9 | H15: =_Calc!$E$6 | K15: =IF(_Calc!$E$11="","—",_Calc!$E$11)
B16: Contas, poupança, carteira e investimentos | E16: Compras ainda não quitadas | H16: =IF(_Calc!$E$7>0,TEXT(_Calc!$E$7,"0")&" em atraso","Nenhuma em atraso") | K16: =IF(_Calc!$E$12>0,TEXT(_Calc!$E$12,"#,##0.00")&" no mês","Sem despesas no mês")
B18: Gastos por categoria | H18: Distribuição das despesas
B19: CATEGORIA | D19: GASTO | E19: % DO TOTAL | F19: PESO RELATIVO
B20: =IF(_Calc!$L$15="","",_Calc!$L$15) | D20: =_Calc!$M$15 | E20: =IF(_Calc!$L$15="","",_Calc!$N$15) | F20: =IF(_Calc!$L$15="","",REPT("█",MAX(1,ROUND(_Calc!$M$15/MAX(_Calc!$M$15,1)*14,0))))
B21: =IF(_Calc!$L$16="","",_Calc!$L$16) | D21: =_Calc!$M$16 | E21: =IF(_Calc!$L$16="","",_Calc!$N$16) | F21: =IF(_Calc!$L$16="","",REPT("█",MAX(1,ROUND(_Calc!$M$16/MAX(_Calc!$M$15,1)*14,0))))
B22: =IF(_Calc!$L$17="","",_Calc!$L$17) | D22: =_Calc!$M$17 | E22: =IF(_Calc!$L$17="","",_Calc!$N$17) | F22: =IF(_Calc!$L$17="","",REPT("█",MAX(1,ROUND(_Calc!$M$17/MAX(_Calc!$M$15,1)*14,0))))
B23: =IF(_Calc!$L$18="","",_Calc!$L$18) | D23: =_Calc!$M$18 | E23: =IF(_Calc!$L$18="","",_Calc!$N$18) | F23: =IF(_Calc!$L$18="","",REPT("█",MAX(1,ROUND(_Calc!$M$18/MAX(_Calc!$M$15,1)*14,0))))
B24: =IF(_Calc!$L$19="","",_Calc!$L$19) | D24: =_Calc!$M$19 | E24: =IF(_Calc!$L$19="","",_Calc!$N$19) | F24: =IF(_Calc!$L$19="","",REPT("█",MAX(1,ROUND(_Calc!$M$19/MAX(_Calc!$M$15,1)*14,0))))
B25: =IF(_Calc!$L$20="","",_Calc!$L$20) | D25: =_Calc!$M$20 | E25: =IF(_Calc!$L$20="","",_Calc!$N$20) | F25: =IF(_Calc!$L$20="","",REPT("█",MAX(1,ROUND(_Calc!$M$20/MAX(_Calc!$M$15,1)*14,0))))
B26: =IF(_Calc!$L$21="","",_Calc!$L$21) | D26: =_Calc!$M$21 | E26: =IF(_Calc!$L$21="","",_Calc!$N$21) | F26: =IF(_Calc!$L$21="","",REPT("█",MAX(1,ROUND(_Calc!$M$21/MAX(_Calc!$M$15,1)*14,0))))
B27: =IF(_Calc!$L$22="","",_Calc!$L$22) | D27: =_Calc!$M$22 | E27: =IF(_Calc!$L$22="","",_Calc!$N$22) | F27: =IF(_Calc!$L$22="","",REPT("█",MAX(1,ROUND(_Calc!$M$22/MAX(_Calc!$M$15,1)*14,0))))
B28: =IF(_Calc!$L$23="","",_Calc!$L$23) | D28: =_Calc!$M$23 | E28: =IF(_Calc!$L$23="","",_Calc!$N$23) | F28: =IF(_Calc!$L$23="","",REPT("█",MAX(1,ROUND(_Calc!$M$23/MAX(_Calc!$M$15,1)*14,0))))
B29: =IF(_Calc!$L$24="","",_Calc!$L$24) | D29: =_Calc!$M$24 | E29: =IF(_Calc!$L$24="","",_Calc!$N$24) | F29: =IF(_Calc!$L$24="","",REPT("█",MAX(1,ROUND(_Calc!$M$24/MAX(_Calc!$M$15,1)*14,0))))
B32: Receitas × despesas · últimos 6 meses | H32: Despesas por dia do mês
B48: Orçamento × realizado | H48: Vilões do mês · maiores aumentos vs mês anterior
B49: CATEGORIA | D49: LIMITE | E49: GASTO | F49: % USADO | G49: SITUAÇÃO | H49: CATEGORIA | J49: ANTERIOR | K49: ATUAL | L49: AUMENTO | M49: %
B50: =IF(_Calc!$L$61="","",_Calc!$L$61) | D50: =_Calc!$M$61 | E50: =_Calc!$N$61 | F50: =IF(_Calc!$L$61="","",_Calc!$O$61) | G50: =IF(_Calc!$L$61="","",IF(_Calc!$O$61>=1,"Estourou",IF(_Calc!$O$61>=0.8,"Atenção","No limite"))) | H50: =IF(_Calc!$T$15="","",_Calc!$T$15) | J50: =IF(_Calc!$T$15="","",_Calc!$U$15) | K50: =IF(_Calc!$T$15="","",_Calc!$V$15) | L50: =IF(_Calc!$T$15="","",_Calc!$W$15) | M50: =IF(_Calc!$T$15="","",_Calc!$X$15)
B51: =IF(_Calc!$L$62="","",_Calc!$L$62) | D51: =_Calc!$M$62 | E51: =_Calc!$N$62 | F51: =IF(_Calc!$L$62="","",_Calc!$O$62) | G51: =IF(_Calc!$L$62="","",IF(_Calc!$O$62>=1,"Estourou",IF(_Calc!$O$62>=0.8,"Atenção","No limite"))) | H51: =IF(_Calc!$T$16="","",_Calc!$T$16) | J51: =IF(_Calc!$T$16="","",_Calc!$U$16) | K51: =IF(_Calc!$T$16="","",_Calc!$V$16) | L51: =IF(_Calc!$T$16="","",_Calc!$W$16) | M51: =IF(_Calc!$T$16="","",_Calc!$X$16)
B52: =IF(_Calc!$L$63="","",_Calc!$L$63) | D52: =_Calc!$M$63 | E52: =_Calc!$N$63 | F52: =IF(_Calc!$L$63="","",_Calc!$O$63) | G52: =IF(_Calc!$L$63="","",IF(_Calc!$O$63>=1,"Estourou",IF(_Calc!$O$63>=0.8,"Atenção","No limite"))) | H52: =IF(_Calc!$T$17="","",_Calc!$T$17) | J52: =IF(_Calc!$T$17="","",_Calc!$U$17) | K52: =IF(_Calc!$T$17="","",_Calc!$V$17) | L52: =IF(_Calc!$T$17="","",_Calc!$W$17) | M52: =IF(_Calc!$T$17="","",_Calc!$X$17)
B53: =IF(_Calc!$L$64="","",_Calc!$L$64) | D53: =_Calc!$M$64 | E53: =_Calc!$N$64 | F53: =IF(_Calc!$L$64="","",_Calc!$O$64) | G53: =IF(_Calc!$L$64="","",IF(_Calc!$O$64>=1,"Estourou",IF(_Calc!$O$64>=0.8,"Atenção","No limite"))) | H53: =IF(_Calc!$T$18="","",_Calc!$T$18) | J53: =IF(_Calc!$T$18="","",_Calc!$U$18) | K53: =IF(_Calc!$T$18="","",_Calc!$V$18) | L53: =IF(_Calc!$T$18="","",_Calc!$W$18) | M53: =IF(_Calc!$T$18="","",_Calc!$X$18)
B54: =IF(_Calc!$L$65="","",_Calc!$L$65) | D54: =_Calc!$M$65 | E54: =_Calc!$N$65 | F54: =IF(_Calc!$L$65="","",_Calc!$O$65) | G54: =IF(_Calc!$L$65="","",IF(_Calc!$O$65>=1,"Estourou",IF(_Calc!$O$65>=0.8,"Atenção","No limite"))) | H54: =IF(_Calc!$T$19="","",_Calc!$T$19) | J54: =IF(_Calc!$T$19="","",_Calc!$U$19) | K54: =IF(_Calc!$T$19="","",_Calc!$V$19) | L54: =IF(_Calc!$T$19="","",_Calc!$W$19) | M54: =IF(_Calc!$T$19="","",_Calc!$X$19)
B55: =IF(_Calc!$L$66="","",_Calc!$L$66) | D55: =_Calc!$M$66 | E55: =_Calc!$N$66 | F55: =IF(_Calc!$L$66="","",_Calc!$O$66) | G55: =IF(_Calc!$L$66="","",IF(_Calc!$O$66>=1,"Estourou",IF(_Calc!$O$66>=0.8,"Atenção","No limite")))
B56: =IF(_Calc!$L$67="","",_Calc!$L$67) | D56: =_Calc!$M$67 | E56: =_Calc!$N$67 | F56: =IF(_Calc!$L$67="","",_Calc!$O$67) | G56: =IF(_Calc!$L$67="","",IF(_Calc!$O$67>=1,"Estourou",IF(_Calc!$O$67>=0.8,"Atenção","No limite"))) | H56: Vilões são as categorias cujo gasto mais cresceu em reais em relação ao mês anterior. Se a lista estiver vazia, nenhum gasto subiu.
B57: =IF(_Calc!$L$68="","",_Calc!$L$68) | D57: =_Calc!$M$68 | E57: =_Calc!$N$68 | F57: =IF(_Calc!$L$68="","",_Calc!$O$68) | G57: =IF(_Calc!$L$68="","",IF(_Calc!$O$68>=1,"Estourou",IF(_Calc!$O$68>=0.8,"Atenção","No limite")))
B59: Maiores despesas do mês | H59: Contas a pagar · pendentes até o fim do mês
B60: DATA | C60: DESCRIÇÃO | F60: CATEGORIA | G60: VALOR | H60: VENCIMENTO | I60: DESCRIÇÃO | L60: VALOR | M60: SITUAÇÃO
B61: =IF(_Calc!$C$130>0,INDEX('Lançamentos'!$B:$B,_Calc!$C$130),"") | C61: =IF(_Calc!$C$130>0,INDEX('Lançamentos'!$D:$D,_Calc!$C$130),"") | F61: =IF(_Calc!$C$130>0,INDEX('Lançamentos'!$F:$F,_Calc!$C$130)&"","") | G61: =IF(_Calc!$C$130>0,INDEX('Lançamentos'!$E:$E,_Calc!$C$130),"") | H61: =IF(_Calc!$D$145>0,_Calc!$C$145,"") | I61: =IF(_Calc!$D$145>0,INDEX('Lançamentos'!$D:$D,_Calc!$D$145),"") | L61: =IF(_Calc!$D$145>0,INDEX('Lançamentos'!$E:$E,_Calc!$D$145),"") | M61: =IF(_Calc!$D$145=0,"",IF(_Calc!$C$145<HOJE,"Atrasada",IF(_Calc!$C$145=HOJE,"Vence hoje","No prazo")))
B62: =IF(_Calc!$C$131>0,INDEX('Lançamentos'!$B:$B,_Calc!$C$131),"") | C62: =IF(_Calc!$C$131>0,INDEX('Lançamentos'!$D:$D,_Calc!$C$131),"") | F62: =IF(_Calc!$C$131>0,INDEX('Lançamentos'!$F:$F,_Calc!$C$131)&"","") | G62: =IF(_Calc!$C$131>0,INDEX('Lançamentos'!$E:$E,_Calc!$C$131),"") | H62: =IF(_Calc!$D$146>0,_Calc!$C$146,"") | I62: =IF(_Calc!$D$146>0,INDEX('Lançamentos'!$D:$D,_Calc!$D$146),"") | L62: =IF(_Calc!$D$146>0,INDEX('Lançamentos'!$E:$E,_Calc!$D$146),"") | M62: =IF(_Calc!$D$146=0,"",IF(_Calc!$C$146<HOJE,"Atrasada",IF(_Calc!$C$146=HOJE,"Vence hoje","No prazo")))
B63: =IF(_Calc!$C$132>0,INDEX('Lançamentos'!$B:$B,_Calc!$C$132),"") | C63: =IF(_Calc!$C$132>0,INDEX('Lançamentos'!$D:$D,_Calc!$C$132),"") | F63: =IF(_Calc!$C$132>0,INDEX('Lançamentos'!$F:$F,_Calc!$C$132)&"","") | G63: =IF(_Calc!$C$132>0,INDEX('Lançamentos'!$E:$E,_Calc!$C$132),"") | H63: =IF(_Calc!$D$147>0,_Calc!$C$147,"") | I63: =IF(_Calc!$D$147>0,INDEX('Lançamentos'!$D:$D,_Calc!$D$147),"") | L63: =IF(_Calc!$D$147>0,INDEX('Lançamentos'!$E:$E,_Calc!$D$147),"") | M63: =IF(_Calc!$D$147=0,"",IF(_Calc!$C$147<HOJE,"Atrasada",IF(_Calc!$C$147=HOJE,"Vence hoje","No prazo")))
B64: =IF(_Calc!$C$133>0,INDEX('Lançamentos'!$B:$B,_Calc!$C$133),"") | C64: =IF(_Calc!$C$133>0,INDEX('Lançamentos'!$D:$D,_Calc!$C$133),"") | F64: =IF(_Calc!$C$133>0,INDEX('Lançamentos'!$F:$F,_Calc!$C$133)&"","") | G64: =IF(_Calc!$C$133>0,INDEX('Lançamentos'!$E:$E,_Calc!$C$133),"") | H64: =IF(_Calc!$D$148>0,_Calc!$C$148,"") | I64: =IF(_Calc!$D$148>0,INDEX('Lançamentos'!$D:$D,_Calc!$D$148),"") | L64: =IF(_Calc!$D$148>0,INDEX('Lançamentos'!$E:$E,_Calc!$D$148),"") | M64: =IF(_Calc!$D$148=0,"",IF(_Calc!$C$148<HOJE,"Atrasada",IF(_Calc!$C$148=HOJE,"Vence hoje","No prazo")))
B65: =IF(_Calc!$C$134>0,INDEX('Lançamentos'!$B:$B,_Calc!$C$134),"") | C65: =IF(_Calc!$C$134>0,INDEX('Lançamentos'!$D:$D,_Calc!$C$134),"") | F65: =IF(_Calc!$C$134>0,INDEX('Lançamentos'!$F:$F,_Calc!$C$134)&"","") | G65: =IF(_Calc!$C$134>0,INDEX('Lançamentos'!$E:$E,_Calc!$C$134),"") | H65: =IF(_Calc!$D$149>0,_Calc!$C$149,"") | I65: =IF(_Calc!$D$149>0,INDEX('Lançamentos'!$D:$D,_Calc!$D$149),"") | L65: =IF(_Calc!$D$149>0,INDEX('Lançamentos'!$E:$E,_Calc!$D$149),"") | M65: =IF(_Calc!$D$149=0,"",IF(_Calc!$C$149<HOJE,"Atrasada",IF(_Calc!$C$149=HOJE,"Vence hoje","No prazo")))
B66: =IF(_Calc!$C$135>0,INDEX('Lançamentos'!$B:$B,_Calc!$C$135),"") | C66: =IF(_Calc!$C$135>0,INDEX('Lançamentos'!$D:$D,_Calc!$C$135),"") | F66: =IF(_Calc!$C$135>0,INDEX('Lançamentos'!$F:$F,_Calc!$C$135)&"","") | G66: =IF(_Calc!$C$135>0,INDEX('Lançamentos'!$E:$E,_Calc!$C$135),"") | H66: =IF(_Calc!$D$150>0,_Calc!$C$150,"") | I66: =IF(_Calc!$D$150>0,INDEX('Lançamentos'!$D:$D,_Calc!$D$150),"") | L66: =IF(_Calc!$D$150>0,INDEX('Lançamentos'!$E:$E,_Calc!$D$150),"") | M66: =IF(_Calc!$D$150=0,"",IF(_Calc!$C$150<HOJE,"Atrasada",IF(_Calc!$C$150=HOJE,"Vence hoje","No prazo")))
B67: =IF(_Calc!$C$136>0,INDEX('Lançamentos'!$B:$B,_Calc!$C$136),"") | C67: =IF(_Calc!$C$136>0,INDEX('Lançamentos'!$D:$D,_Calc!$C$136),"") | F67: =IF(_Calc!$C$136>0,INDEX('Lançamentos'!$F:$F,_Calc!$C$136)&"","") | G67: =IF(_Calc!$C$136>0,INDEX('Lançamentos'!$E:$E,_Calc!$C$136),"") | H67: =IF(_Calc!$D$151>0,_Calc!$C$151,"") | I67: =IF(_Calc!$D$151>0,INDEX('Lançamentos'!$D:$D,_Calc!$D$151),"") | L67: =IF(_Calc!$D$151>0,INDEX('Lançamentos'!$E:$E,_Calc!$D$151),"") | M67: =IF(_Calc!$D$151=0,"",IF(_Calc!$C$151<HOJE,"Atrasada",IF(_Calc!$C$151=HOJE,"Vence hoje","No prazo")))
B68: =IF(_Calc!$C$137>0,INDEX('Lançamentos'!$B:$B,_Calc!$C$137),"") | C68: =IF(_Calc!$C$137>0,INDEX('Lançamentos'!$D:$D,_Calc!$C$137),"") | F68: =IF(_Calc!$C$137>0,INDEX('Lançamentos'!$F:$F,_Calc!$C$137)&"","") | G68: =IF(_Calc!$C$137>0,INDEX('Lançamentos'!$E:$E,_Calc!$C$137),"") | H68: =IF(_Calc!$D$152>0,_Calc!$C$152,"") | I68: =IF(_Calc!$D$152>0,INDEX('Lançamentos'!$D:$D,_Calc!$D$152),"") | L68: =IF(_Calc!$D$152>0,INDEX('Lançamentos'!$E:$E,_Calc!$D$152),"") | M68: =IF(_Calc!$D$152=0,"",IF(_Calc!$C$152<HOJE,"Atrasada",IF(_Calc!$C$152=HOJE,"Vence hoje","No prazo")))
B69: =IF(_Calc!$C$138>0,INDEX('Lançamentos'!$B:$B,_Calc!$C$138),"") | C69: =IF(_Calc!$C$138>0,INDEX('Lançamentos'!$D:$D,_Calc!$C$138),"") | F69: =IF(_Calc!$C$138>0,INDEX('Lançamentos'!$F:$F,_Calc!$C$138)&"","") | G69: =IF(_Calc!$C$138>0,INDEX('Lançamentos'!$E:$E,_Calc!$C$138),"") | H69: =IF(_Calc!$D$153>0,_Calc!$C$153,"") | I69: =IF(_Calc!$D$153>0,INDEX('Lançamentos'!$D:$D,_Calc!$D$153),"") | L69: =IF(_Calc!$D$153>0,INDEX('Lançamentos'!$E:$E,_Calc!$D$153),"") | M69: =IF(_Calc!$D$153=0,"",IF(_Calc!$C$153<HOJE,"Atrasada",IF(_Calc!$C$153=HOJE,"Vence hoje","No prazo")))
B70: =IF(_Calc!$C$139>0,INDEX('Lançamentos'!$B:$B,_Calc!$C$139),"") | C70: =IF(_Calc!$C$139>0,INDEX('Lançamentos'!$D:$D,_Calc!$C$139),"") | F70: =IF(_Calc!$C$139>0,INDEX('Lançamentos'!$F:$F,_Calc!$C$139)&"","") | G70: =IF(_Calc!$C$139>0,INDEX('Lançamentos'!$E:$E,_Calc!$C$139),"") | H70: =IF(_Calc!$D$154>0,_Calc!$C$154,"") | I70: =IF(_Calc!$D$154>0,INDEX('Lançamentos'!$D:$D,_Calc!$D$154),"") | L70: =IF(_Calc!$D$154>0,INDEX('Lançamentos'!$E:$E,_Calc!$D$154),"") | M70: =IF(_Calc!$D$154=0,"",IF(_Calc!$C$154<HOJE,"Atrasada",IF(_Calc!$C$154=HOJE,"Vence hoje","No prazo")))
B72: Contas e cartões · saldo atual | H72: Resumo do ano
B73: CONTA | D73: TIPO | F73: SALDO | H73: INDICADOR | L73: VALOR
B74: =IF(_Calc!$A$160="","",_Calc!$A$160) | D74: =IF(_Calc!$A$160="","",_Calc!$B$160) | F74: =IF(_Calc!$A$160="","",_Calc!$D$160) | H74: Receitas no ano | L74: =_Calc!$G$190
B75: =IF(_Calc!$A$161="","",_Calc!$A$161) | D75: =IF(_Calc!$A$161="","",_Calc!$B$161) | F75: =IF(_Calc!$A$161="","",_Calc!$D$161) | H75: Despesas no ano | L75: =_Calc!$G$191
B76: =IF(_Calc!$A$162="","",_Calc!$A$162) | D76: =IF(_Calc!$A$162="","",_Calc!$B$162) | F76: =IF(_Calc!$A$162="","",_Calc!$D$162) | H76: Resultado no ano | L76: =_Calc!$G$192
B77: =IF(_Calc!$A$163="","",_Calc!$A$163) | D77: =IF(_Calc!$A$163="","",_Calc!$B$163) | F77: =IF(_Calc!$A$163="","",_Calc!$D$163) | H77: Média mensal de despesas | L77: =_Calc!$G$193
B78: =IF(_Calc!$A$164="","",_Calc!$A$164) | D78: =IF(_Calc!$A$164="","",_Calc!$B$164) | F78: =IF(_Calc!$A$164="","",_Calc!$D$164) | H78: Mês de maior despesa | L78: =_Calc!$G$194&IF(_Calc!$G$195>0," · "&TEXT(_Calc!$G$195,"#,##0.00"),"")
B79: =IF(_Calc!$A$165="","",_Calc!$A$165) | D79: =IF(_Calc!$A$165="","",_Calc!$B$165) | F79: =IF(_Calc!$A$165="","",_Calc!$D$165) | H79: Mês de maior economia | L79: =_Calc!$G$196&IF(_Calc!$G$197>0," · "&TEXT(_Calc!$G$197,"#,##0.00"),"")
B80: =IF(_Calc!$A$166="","",_Calc!$A$166) | D80: =IF(_Calc!$A$166="","",_Calc!$B$166) | F80: =IF(_Calc!$A$166="","",_Calc!$D$166)
B81: =IF(_Calc!$A$167="","",_Calc!$A$167) | D81: =IF(_Calc!$A$167="","",_Calc!$B$167) | F81: =IF(_Calc!$A$167="","",_Calc!$D$167)
B83: Painel gerado por fórmulas a partir da aba Lançamentos. Não edite as fórmulas: altere apenas os filtros do topo. Dados de lançamentos são mantidos pelo app Orange Finance.

Sheet Lançamentos
A1: id | B1: data | C1: tipo | D1: descricao | E1: valor | F1: categoria | G1: conta | H1: conta_destino | I1: titular | J1: status | K1: observacoes | L1: serie_id | M1: parcela_n | N1: parcelas_total | O1: frequencia | P1: ciclo_fatura | Q1: origem | R1: criado_em | S1: atualizado_em | T1: excluido_em | U1: rev
A2: ced66b44-7f45-b096-d380-1b73c446ab8c | B2: 46235 | C2: Despesa | D2: Curso de idiomas | E2: 189 | F2: Educação | G2: Conta corrente | J2: Pago | Q2: exemplo | R2: 2026-10-17T12:00:00Z | S2: 2026-10-17T12:00:00Z | U2: 1
A3: 5b4c8012-ede7-bd0c-ffb8-8309fadb8908 | B3: 46236 | C3: Despesa | D3: Mercado | E3: 412.8 | F3: Mercado | G3: Cartão de crédito | J3: Pago | P3: 46262 | Q3: exemplo | R3: 2026-10-17T12:00:00Z | S3: 2026-10-17T12:00:00Z | U3: 1
A4: e060a724-2411-4258-751b-4c8349a047dc | B4: 46237 | C4: Despesa | D4: Padaria | E4: 24.5 | F4: Alimentação | G4: Carteira | J4: Pago | Q4: exemplo | R4: 2026-10-17T12:00:00Z | S4: 2026-10-17T12:00:00Z | U4: 1
A5: 5071950e-adec-6f11-7d83-6e77af67d461 | B5: 46237 | C5: Despesa | D5: Streaming de vídeo | E5: 55.9 | F5: Assinaturas | G5: Cartão de crédito | J5: Pago | P5: 46262 | Q5: exemplo | R5: 2026-10-17T12:00:00Z | S5: 2026-10-17T12:00:00Z | U5: 1
A6: 59001ac9-4063-29bc-65b0-0a2d35d14880 | B6: 46238 | C6: Despesa | D6: Streaming de música | E6: 21.9 | F6: Assinaturas | G6: Cartão de crédito | J6: Pago | P6: 46262 | Q6: exemplo | R6: 2026-10-17T12:00:00Z | S6: 2026-10-17T12:00:00Z | U6: 1
A7: ac9f21df-74f0-9af5-b361-8e1ca06d7a69 | B7: 46238 | C7: Despesa | D7: Transporte por app | E7: 28.4 | F7: Transporte | G7: Cartão de crédito | J7: Pago | P7: 46262 | Q7: exemplo | R7: 2026-10-17T12:00:00Z | S7: 2026-10-17T12:00:00Z | U7: 1
A8: 6bad6be2-8e7a-a6e9-9f19-950499dd251d | B8: 46239 | C8: Despesa | D8: Aluguel | E8: 2100 | F8: Moradia | G8: Conta corrente | J8: Pago | Q8: exemplo | R8: 2026-10-17T12:00:00Z | S8: 2026-10-17T12:00:00Z | U8: 1
A9: f38b2ffc-80a4-df5a-51c9-bc701e7ea419 | B9: 46239 | C9: Receita | D9: Salário | E9: 6200 | F9: Salário | G9: Conta corrente | J9: Pago | Q9: exemplo | R9: 2026-10-17T12:00:00Z | S9: 2026-10-17T12:00:00Z | U9: 1
A10: e26b524a-ce0d-8d87-7a98-b9acb2c55523 | B10: 46240 | C10: Despesa | D10: Combustível | E10: 224 | F10: Transporte | G10: Conta corrente | J10: Pago | Q10: exemplo | R10: 2026-10-17T12:00:00Z | S10: 2026-10-17T12:00:00Z | U10: 1
A11: 5e6c9992-b5fb-12e0-d909-0b8906555096 | B11: 46240 | C11: Despesa | D11: Padaria | E11: 31 | F11: Alimentação | G11: Conta corrente | J11: Pago | Q11: exemplo | R11: 2026-10-17T12:00:00Z | S11: 2026-10-17T12:00:00Z | U11: 1
A12: 511070a7-4a41-f8e4-d4d6-d278089b5123 | B12: 46240 | C12: Transferência | D12: Reserva mensal | E12: 1000 | G12: Conta corrente | H12: Poupança | J12: Pago | Q12: exemplo | R12: 2026-10-17T12:00:00Z | S12: 2026-10-17T12:00:00Z | U12: 1
A13: 2106119e-c40d-31b5-397a-762393550840 | B13: 46241 | C13: Despesa | D13: Restaurante | E13: 96 | F13: Alimentação | G13: Cartão de crédito | J13: Pago | P13: 46262 | Q13: exemplo | R13: 2026-10-17T12:00:00Z | S13: 2026-10-17T12:00:00Z | U13: 1
A14: f3f49249-dc28-ff90-a5ae-c7978306d03b | B14: 46241 | C14: Receita | D14: Salário | E14: 4800 | F14: Salário | G14: Conta corrente | J14: Pago | Q14: exemplo | R14: 2026-10-17T12:00:00Z | S14: 2026-10-17T12:00:00Z | U14: 1
A15: 1919e93a-d117-45ad-4988-93101c593af5 | B15: 46242 | C15: Despesa | D15: Plano de saúde | E15: 520 | F15: Saúde | G15: Conta corrente | J15: Pago | Q15: exemplo | R15: 2026-10-17T12:00:00Z | S15: 2026-10-17T12:00:00Z | U15: 1
A16: e4163207-d094-4996-02f0-ee99731c9452 | B16: 46243 | C16: Despesa | D16: Academia | E16: 109.9 | F16: Cuidados pessoais | G16: Conta corrente | J16: Pago | Q16: exemplo | R16: 2026-10-17T12:00:00Z | S16: 2026-10-17T12:00:00Z | U16: 1
A17: 192f09a9-cfd8-c364-eab4-2bd67528ea79 | B17: 46243 | C17: Transferência | D17: Aporte investimentos | E17: 500 | G17: Poupança | H17: Investimentos | J17: Pago | Q17: exemplo | R17: 2026-10-17T12:00:00Z | S17: 2026-10-17T12:00:00Z | U17: 1
A18: bef7e268-ffe9-76ab-6058-1ccace1d62e0 | B18: 46243 | C18: Despesa | D18: Mercado | E18: 388.45 | F18: Mercado | G18: Cartão de crédito | J18: Pago | P18: 46262 | Q18: exemplo | R18: 2026-10-17T12:00:00Z | S18: 2026-10-17T12:00:00Z | U18: 1
A19: d7a7a3cc-8c3d-5f16-9293-de8fc88b2875 | B19: 46244 | C19: Despesa | D19: Condomínio | E19: 450 | F19: Moradia | G19: Conta corrente | J19: Pago | Q19: exemplo | R19: 2026-10-17T12:00:00Z | S19: 2026-10-17T12:00:00Z | U19: 1
A20: fcbad167-f5a9-ca5f-edf1-65dab6eafff5 | B20: 46244 | C20: Despesa | D20: Transporte por app | E20: 41.9 | F20: Transporte | G20: Cartão de crédito | J20: Pago | P20: 46262 | Q20: exemplo | R20: 2026-10-17T12:00:00Z | S20: 2026-10-17T12:00:00Z | U20: 1
A21: 0879d955-025f-f87c-44df-8a13d4f398ee | B21: 46245 | C21: Despesa | D21: Farmácia | E21: 87.6 | F21: Saúde | G21: Conta corrente | J21: Pago | Q21: exemplo | R21: 2026-10-17T12:00:00Z | S21: 2026-10-17T12:00:00Z | U21: 1
A22: 66160227-1737-1472-6c16-72297608d942 | B22: 46245 | C22: Despesa | D22: Padaria | E22: 18.9 | F22: Alimentação | G22: Carteira | J22: Pago | Q22: exemplo | R22: 2026-10-17T12:00:00Z | S22: 2026-10-17T12:00:00Z | U22: 1
A23: 7dabe929-c4a3-34bf-c6cd-75e9bb049a79 | B23: 46246 | C23: Despesa | D23: Energia elétrica | E23: 212.4 | F23: Contas e serviços | G23: Conta corrente | J23: Pago | Q23: exemplo | R23: 2026-10-17T12:00:00Z | S23: 2026-10-17T12:00:00Z | U23: 1
A24: e842997d-a9f5-307c-8ece-78b06f29a9f1 | B24: 46246 | C24: Despesa | D24: Salão | E24: 120 | F24: Cuidados pessoais | G24: Conta corrente | J24: Pago | Q24: exemplo | R24: 2026-10-17T12:00:00Z | S24: 2026-10-17T12:00:00Z | U24: 1
A25: e306f0c4-85f1-84e0-b464-c554f675299b | B25: 46247 | C25: Despesa | D25: Delivery | E25: 74.5 | F25: Alimentação | G25: Cartão de crédito | J25: Pago | P25: 46262 | Q25: exemplo | R25: 2026-10-17T12:00:00Z | S25: 2026-10-17T12:00:00Z | U25: 1
A26: 7d510557-ed4d-19b8-85dc-0a68cdb54088 | B26: 46248 | C26: Despesa | D26: Cinema | E26: 68 | F26: Lazer | G26: Cartão de crédito | J26: Pago | P26: 46262 | Q26: exemplo | R26: 2026-10-17T12:00:00Z | S26: 2026-10-17T12:00:00Z | U26: 1
A27: 81a0ba05-6ce9-da66-1dcf-884cde0279e1 | B27: 46248 | C27: Despesa | D27: Padaria | E27: 42.3 | F27: Alimentação | G27: Conta corrente | J27: Pago | Q27: exemplo | R27: 2026-10-17T12:00:00Z | S27: 2026-10-17T12:00:00Z | U27: 1
A28: 70eb9a0a-9626-3ae6-c5e8-18fac0433cbd | B28: 46249 | C28: Despesa | D28: Internet | E28: 119.9 | F28: Contas e serviços | G28: Conta corrente | J28: Pago | Q28: exemplo | R28: 2026-10-17T12:00:00Z | S28: 2026-10-17T12:00:00Z | U28: 1
A29: 82e26123-7776-c655-7c4e-4248b1515fff | B29: 46250 | C29: Despesa | D29: Camiseta e tênis | E29: 289.9 | F29: Vestuário | G29: Cartão de crédito | J29: Pago | P29: 46262 | Q29: exemplo | R29: 2026-10-17T12:00:00Z | S29: 2026-10-17T12:00:00Z | U29: 1
A30: b91dddd9-1389-b372-a341-738c837a7935 | B30: 46250 | C30: Despesa | D30: Mercado | E30: 436.2 | F30: Mercado | G30: Cartão de crédito | J30: Pago | P30: 46262 | Q30: exemplo | R30: 2026-10-17T12:00:00Z | S30: 2026-10-17T12:00:00Z | U30: 1
A31: ff8b2a6a-ab74-fe57-66ee-bc578f4ecb4f | B31: 46251 | C31: Despesa | D31: Transporte por app | E31: 23.7 | F31: Transporte | G31: Cartão de crédito | J31: Pago | P31: 46262 | Q31: exemplo | R31: 2026-10-17T12:00:00Z | S31: 2026-10-17T12:00:00Z | U31: 1
A32: 14aa4e71-9d3c-7dec-00a6-1f933d6c51e3 | B32: 46252 | C32: Despesa | D32: Água | E32: 88.3 | F32: Contas e serviços | G32: Conta corrente | J32: Pago | Q32: exemplo | R32: 2026-10-17T12:00:00Z | S32: 2026-10-17T12:00:00Z | U32: 1
A33: 423674a6-864f-a3f3-eab0-6e9b65ed0de4 | B33: 46253 | C33: Despesa | D33: Padaria | E33: 27.6 | F33: Alimentação | G33: Carteira | J33: Pago | Q33: exemplo | R33: 2026-10-17T12:00:00Z | S33: 2026-10-17T12:00:00Z | U33: 1
A34: 4b5c1a95-33d9-1808-6edd-77d866e61127 | B34: 46254 | C34: Despesa | D34: Combustível | E34: 231.5 | F34: Transporte | G34: Conta corrente | J34: Pago | Q34: exemplo | R34: 2026-10-17T12:00:00Z | S34: 2026-10-17T12:00:00Z | U34: 1
A35: 78549014-6ded-c86a-9f4f-b02bb7a1774f | B35: 46255 | C35: Despesa | D35: Restaurante | E35: 128 | F35: Alimentação | G35: Cartão de crédito | J35: Pago | P35: 46293 | Q35: exemplo | R35: 2026-10-17T12:00:00Z | S35: 2026-10-17T12:00:00Z | U35: 1
A36: 42969a50-3328-8e16-ebe8-0fa95c24c1ae | B36: 46256 | C36: Despesa | D36: Show | E36: 190 | F36: Lazer | G36: Cartão de crédito | J36: Pago | P36: 46293 | Q36: exemplo | R36: 2026-10-17T12:00:00Z | S36: 2026-10-17T12:00:00Z | U36: 1
A37: 89be9c1c-8eb5-140f-16f4-488157241955 | B37: 46257 | C37: Despesa | D37: Mercado | E37: 471.9 | F37: Mercado | G37: Cartão de crédito | J37: Pago | P37: 46293 | Q37: exemplo | R37: 2026-10-17T12:00:00Z | S37: 2026-10-17T12:00:00Z | U37: 1
A38: 98e6e5b7-e1cd-7be8-a7d8-3351265c28ea | B38: 46258 | C38: Despesa | D38: Farmácia | E38: 63.2 | F38: Saúde | G38: Conta corrente | J38: Pago | Q38: exemplo | R38: 2026-10-17T12:00:00Z | S38: 2026-10-17T12:00:00Z | U38: 1
A39: 7aac319f-fb75-9e0f-ed1d-9d1690624fe3 | B39: 46259 | C39: Despesa | D39: Padaria | E39: 35.4 | F39: Alimentação | G39: Carteira | J39: Pago | Q39: exemplo | R39: 2026-10-17T12:00:00Z | S39: 2026-10-17T12:00:00Z | U39: 1
A40: 807c7e30-a598-d0db-ccbf-d2ec8c53765f | B40: 46260 | C40: Despesa | D40: Transporte por app | E40: 36.2 | F40: Transporte | G40: Cartão de crédito | J40: Pago | P40: 46293 | Q40: exemplo | R40: 2026-10-17T12:00:00Z | S40: 2026-10-17T12:00:00Z | U40: 1
A41: d9814559-3a9a-fa39-e261-e34a7b6bc3c6 | B41: 46261 | C41: Despesa | D41: Delivery | E41: 62.9 | F41: Alimentação | G41: Cartão de crédito | J41: Pago | P41: 46293 | Q41: exemplo | R41: 2026-10-17T12:00:00Z | S41: 2026-10-17T12:00:00Z | U41: 1
A42: f272c2ef-4ab8-bd10-6398-9ab940676334 | B42: 46262 | C42: Transferência | D42: Pagamento da fatura | E42: 1850 | G42: Conta corrente | H42: Cartão de crédito | J42: Pago | Q42: exemplo | R42: 2026-10-17T12:00:00Z | S42: 2026-10-17T12:00:00Z | U42: 1
A43: e5121482-3929-2d22-e255-accb1a466884 | B43: 46265 | C43: Receita | D43: Rendimentos poupança | E43: 78 | F43: Rendimentos | G43: Poupança | J43: Pago | Q43: exemplo | R43: 2026-10-17T12:00:00Z | S43: 2026-10-17T12:00:00Z | U43: 1
A44: a5497863-210f-4de3-053d-82cbe0b89bcb | B44: 46266 | C44: Despesa | D44: Curso de idiomas | E44: 189 | F44: Educação | G44: Conta corrente | J44: Pago | Q44: exemplo | R44: 2026-10-17T12:00:00Z | S44: 2026-10-17T12:00:00Z | U44: 1
A45: 279e6933-5b74-c718-a2aa-216ac1f6192b | B45: 46267 | C45: Despesa | D45: Mercado | E45: 412.8 | F45: Mercado | G45: Cartão de crédito | J45: Pago | P45: 46293 | Q45: exemplo | R45: 2026-10-17T12:00:00Z | S45: 2026-10-17T12:00:00Z | U45: 1
A46: 9682e074-7915-72d5-3911-c9b08bb9c912 | B46: 46268 | C46: Despesa | D46: Padaria | E46: 24.5 | F46: Alimentação | G46: Carteira | J46: Pago | Q46: exemplo | R46: 2026-10-17T12:00:00Z | S46: 2026-10-17T12:00:00Z | U46: 1
A47: c07991d4-0b6e-c6f3-9efe-bfda1eedfcfc | B47: 46268 | C47: Despesa | D47: Streaming de vídeo | E47: 55.9 | F47: Assinaturas | G47: Cartão de crédito | J47: Pago | P47: 46293 | Q47: exemplo | R47: 2026-10-17T12:00:00Z | S47: 2026-10-17T12:00:00Z | U47: 1
A48: ab215122-44be-cdce-f4d4-75ec8be40e7f | B48: 46269 | C48: Despesa | D48: Streaming de música | E48: 21.9 | F48: Assinaturas | G48: Cartão de crédito | J48: Pago | P48: 46293 | Q48: exemplo | R48: 2026-10-17T12:00:00Z | S48: 2026-10-17T12:00:00Z | U48: 1
A49: 1f124a78-e9f9-1484-5377-899a733c6676 | B49: 46269 | C49: Despesa | D49: Transporte por app | E49: 28.4 | F49: Transporte | G49: Cartão de crédito | J49: Pago | P49: 46293 | Q49: exemplo | R49: 2026-10-17T12:00:00Z | S49: 2026-10-17T12:00:00Z | U49: 1
A50: 44371ff3-a607-41f3-1075-a5b0f0acdebe | B50: 46270 | C50: Despesa | D50: Aluguel | E50: 2100 | F50: Moradia | G50: Conta corrente | J50: Pago | Q50: exemplo | R50: 2026-10-17T12:00:00Z | S50: 2026-10-17T12:00:00Z | U50: 1
A51: c8fb4456-b76d-c0c3-b078-22db703e53cf | B51: 46270 | C51: Receita | D51: Salário | E51: 6200 | F51: Salário | G51: Conta corrente | J51: Pago | Q51: exemplo | R51: 2026-10-17T12:00:00Z | S51: 2026-10-17T12:00:00Z | U51: 1
A52: 11cb4ea7-b5fc-684a-adb2-10953bbb492b | B52: 46271 | C52: Despesa | D52: Combustível | E52: 224 | F52: Transporte | G52: Conta corrente | J52: Pago | Q52: exemplo | R52: 2026-10-17T12:00:00Z | S52: 2026-10-17T12:00:00Z | U52: 1
A53: b14ab8e9-e041-2118-991f-77c9f551abfd | B53: 46271 | C53: Despesa | D53: Padaria | E53: 31 | F53: Alimentação | G53: Conta corrente | J53: Pago | Q53: exemplo | R53: 2026-10-17T12:00:00Z | S53: 2026-10-17T12:00:00Z | U53: 1
A54: 2f9e09c9-d828-f123-a945-e7bb290f5d0f | B54: 46271 | C54: Transferência | D54: Reserva mensal | E54: 1000 | G54: Conta corrente | H54: Poupança | J54: Pago | Q54: exemplo | R54: 2026-10-17T12:00:00Z | S54: 2026-10-17T12:00:00Z | U54: 1
A55: e344f1c3-63ac-4f14-1b2b-980ef57585ce | B55: 46272 | C55: Despesa | D55: Restaurante | E55: 96 | F55: Alimentação | G55: Cartão de crédito | J55: Pago | P55: 46293 | Q55: exemplo | R55: 2026-10-17T12:00:00Z | S55: 2026-10-17T12:00:00Z | U55: 1
A56: 73f29c6a-4242-c225-83e2-665af6540600 | B56: 46272 | C56: Receita | D56: Salário | E56: 4800 | F56: Salário | G56: Conta corrente | J56: Pago | Q56: exemplo | R56: 2026-10-17T12:00:00Z | S56: 2026-10-17T12:00:00Z | U56: 1
A57: 1543c8ef-d61b-5e08-eea3-3d4e8bed5b65 | B57: 46273 | C57: Despesa | D57: Plano de saúde | E57: 520 | F57: Saúde | G57: Conta corrente | J57: Pago | Q57: exemplo | R57: 2026-10-17T12:00:00Z | S57: 2026-10-17T12:00:00Z | U57: 1
A58: 3f724926-32e4-034c-cb34-8cea9c31b930 | B58: 46274 | C58: Despesa | D58: Academia | E58: 109.9 | F58: Cuidados pessoais | G58: Conta corrente | J58: Pago | Q58: exemplo | R58: 2026-10-17T12:00:00Z | S58: 2026-10-17T12:00:00Z | U58: 1
A59: 88736737-6ce4-048f-45d6-ac4263d52b10 | B59: 46274 | C59: Transferência | D59: Aporte investimentos | E59: 500 | G59: Poupança | H59: Investimentos | J59: Pago | Q59: exemplo | R59: 2026-10-17T12:00:00Z | S59: 2026-10-17T12:00:00Z | U59: 1
A60: 9543c6c3-aa22-0078-503d-c86b01504585 | B60: 46274 | C60: Despesa | D60: Mercado | E60: 388.45 | F60: Mercado | G60: Cartão de crédito | J60: Pago | P60: 46293 | Q60: exemplo | R60: 2026-10-17T12:00:00Z | S60: 2026-10-17T12:00:00Z | U60: 1
A61: 18bee074-5ec0-c260-7f98-80a6e73c49ea | B61: 46275 | C61: Despesa | D61: Condomínio | E61: 450 | F61: Moradia | G61: Conta corrente | J61: Pago | Q61: exemplo | R61: 2026-10-17T12:00:00Z | S61: 2026-10-17T12:00:00Z | U61: 1
A62: 9e5cf6e9-9255-9248-7771-f894f2e36355 | B62: 46275 | C62: Despesa | D62: Transporte por app | E62: 41.9 | F62: Transporte | G62: Cartão de crédito | J62: Pago | P62: 46293 | Q62: exemplo | R62: 2026-10-17T12:00:00Z | S62: 2026-10-17T12:00:00Z | U62: 1
A63: 0b94a014-2c61-93cc-ebe4-8123a5b0e526 | B63: 46276 | C63: Despesa | D63: Farmácia | E63: 87.6 | F63: Saúde | G63: Conta corrente | J63: Pago | Q63: exemplo | R63: 2026-10-17T12:00:00Z | S63: 2026-10-17T12:00:00Z | U63: 1
A64: 28fdb92d-ab26-6981-6af3-8f6c159d6a38 | B64: 46276 | C64: Despesa | D64: Padaria | E64: 18.9 | F64: Alimentação | G64: Carteira | J64: Pago | Q64: exemplo | R64: 2026-10-17T12:00:00Z | S64: 2026-10-17T12:00:00Z | U64: 1
A65: 694baad6-db4c-9492-bf5f-85e231d06d9c | B65: 46277 | C65: Despesa | D65: Energia elétrica | E65: 231.9 | F65: Contas e serviços | G65: Conta corrente | J65: Pago | Q65: exemplo | R65: 2026-10-17T12:00:00Z | S65: 2026-10-17T12:00:00Z | U65: 1
A66: e1f66c3a-c910-8f89-37fe-43eb87a9ec13 | B66: 46277 | C66: Despesa | D66: Salão | E66: 120 | F66: Cuidados pessoais | G66: Conta corrente | J66: Pago | Q66: exemplo | R66: 2026-10-17T12:00:00Z | S66: 2026-10-17T12:00:00Z | U66: 1
A67: adbafed0-b600-860c-7bdc-fd55304374b3 | B67: 46277 | C67: Despesa | D67: Vestido | E67: 179.9 | F67: Vestuário | G67: Cartão de crédito | J67: Pago | P67: 46293 | Q67: exemplo | R67: 2026-10-17T12:00:00Z | S67: 2026-10-17T12:00:00Z | U67: 1
A68: a5721c6a-58d6-2944-d573-e7bb0d26efa0 | B68: 46278 | C68: Despesa | D68: Delivery | E68: 74.5 | F68: Alimentação | G68: Cartão de crédito | J68: Pago | P68: 46293 | Q68: exemplo | R68: 2026-10-17T12:00:00Z | S68: 2026-10-17T12:00:00Z | U68: 1
A69: a40eecb5-c134-a79b-de3b-7dd373aa881e | B69: 46279 | C69: Despesa | D69: Cinema | E69: 68 | F69: Lazer | G69: Cartão de crédito | J69: Pago | P69: 46293 | Q69: exemplo | R69: 2026-10-17T12:00:00Z | S69: 2026-10-17T12:00:00Z | U69: 1
A70: 96060250-ea3e-7f73-c84c-1884c88f63d6 | B70: 46279 | C70: Despesa | D70: Padaria | E70: 42.3 | F70: Alimentação | G70: Conta corrente | J70: Pago | Q70: exemplo | R70: 2026-10-17T12:00:00Z | S70: 2026-10-17T12:00:00Z | U70: 1
A71: 0397a31d-ea9e-7ab5-730b-89dc2577c324 | B71: 46280 | C71: Despesa | D71: Internet | E71: 119.9 | F71: Contas e serviços | G71: Conta corrente | J71: Pago | Q71: exemplo | R71: 2026-10-17T12:00:00Z | S71: 2026-10-17T12:00:00Z | U71: 1
A72: f32efa03-ed1b-a5c8-c4ff-c64e93043fca | B72: 46281 | C72: Despesa | D72: Mercado | E72: 436.2 | F72: Mercado | G72: Cartão de crédito | J72: Pago | P72: 46293 | Q72: exemplo | R72: 2026-10-17T12:00:00Z | S72: 2026-10-17T12:00:00Z | U72: 1
A73: 34fd02f6-8505-67c2-975c-ef7a27655f91 | B73: 46282 | C73: Despesa | D73: Transporte por app | E73: 23.7 | F73: Transporte | G73: Cartão de crédito | J73: Pago | P73: 46293 | Q73: exemplo | R73: 2026-10-17T12:00:00Z | S73: 2026-10-17T12:00:00Z | U73: 1
A74: f79edc82-2edc-49c1-f71b-d135ec0643b1 | B74: 46283 | C74: Receita | D74: Projeto freelance | E74: 900 | F74: Freelance | G74: Conta corrente | J74: Pago | Q74: exemplo | R74: 2026-10-17T12:00:00Z | S74: 2026-10-17T12:00:00Z | U74: 1
A75: 94a4d29c-7383-d496-000e-05d017985d06 | B75: 46283 | C75: Despesa | D75: Água | E75: 88.3 | F75: Contas e serviços | G75: Conta corrente | J75: Pago | Q75: exemplo | R75: 2026-10-17T12:00:00Z | S75: 2026-10-17T12:00:00Z | U75: 1
A76: ced8c284-63f1-bbbc-697b-65cb81f8c04a | B76: 46284 | C76: Despesa | D76: Padaria | E76: 27.6 | F76: Alimentação | G76: Carteira | J76: Pago | Q76: exemplo | R76: 2026-10-17T12:00:00Z | S76: 2026-10-17T12:00:00Z | U76: 1
A77: 320be3f8-08be-3b07-662f-286b8c1f6387 | B77: 46285 | C77: Despesa | D77: Combustível | E77: 231.5 | F77: Transporte | G77: Conta corrente | J77: Pago | Q77: exemplo | R77: 2026-10-17T12:00:00Z | S77: 2026-10-17T12:00:00Z | U77: 1
A78: 2341bbbe-f4e2-ea68-e505-88a5845074a1 | B78: 46286 | C78: Despesa | D78: Presente de aniversário | E78: 140 | F78: Outros | G78: Conta corrente | J78: Pago | Q78: exemplo | R78: 2026-10-17T12:00:00Z | S78: 2026-10-17T12:00:00Z | U78: 1
A79: 069a306f-f1f0-2f49-c500-29abef3e4144 | B79: 46286 | C79: Despesa | D79: Restaurante | E79: 128 | F79: Alimentação | G79: Cartão de crédito | J79: Pendente | P79: 46323 | Q79: exemplo | R79: 2026-10-17T12:00:00Z | S79: 2026-10-17T12:00:00Z | U79: 1
A80: b870e4e1-b093-e3b4-7df2-fc58dc56dc87 | B80: 46288 | C80: Despesa | D80: Mercado | E80: 471.9 | F80: Mercado | G80: Cartão de crédito | J80: Pendente | P80: 46323 | Q80: exemplo | R80: 2026-10-17T12:00:00Z | S80: 2026-10-17T12:00:00Z | U80: 1
A81: d6c769cb-ee53-2f03-8b75-d02aa5f27419 | B81: 46289 | C81: Despesa | D81: Farmácia | E81: 63.2 | F81: Saúde | G81: Conta corrente | J81: Pago | Q81: exemplo | R81: 2026-10-17T12:00:00Z | S81: 2026-10-17T12:00:00Z | U81: 1
A82: 6041f10e-325a-bdec-ce91-82088520bf0c | B82: 46290 | C82: Despesa | D82: Padaria | E82: 35.4 | F82: Alimentação | G82: Carteira | J82: Pago | Q82: exemplo | R82: 2026-10-17T12:00:00Z | S82: 2026-10-17T12:00:00Z | U82: 1
A83: 9924eb8b-7575-0c2b-561f-8bfe9f93693f | B83: 46291 | C83: Despesa | D83: Transporte por app | E83: 36.2 | F83: Transporte | G83: Cartão de crédito | J83: Pendente | P83: 46323 | Q83: exemplo | R83: 2026-10-17T12:00:00Z | S83: 2026-10-17T12:00:00Z | U83: 1
A84: aecb9e68-53e8-1536-79dc-bc8182a8c712 | B84: 46292 | C84: Despesa | D84: Delivery | E84: 62.9 | F84: Alimentação | G84: Cartão de crédito | J84: Pendente | P84: 46323 | Q84: exemplo | R84: 2026-10-17T12:00:00Z | S84: 2026-10-17T12:00:00Z | U84: 1
A85: 060ecc8a-e0df-f709-6fce-4808b7158e9c | B85: 46293 | C85: Transferência | D85: Pagamento da fatura | E85: 2716.65 | G85: Conta corrente | H85: Cartão de crédito | J85: Pago | Q85: exemplo | R85: 2026-10-17T12:00:00Z | S85: 2026-10-17T12:00:00Z | U85: 1
A86: 7aa95416-ba5c-875c-d7aa-22086cffb0f0 | B86: 46295 | C86: Receita | D86: Rendimentos poupança | E86: 85 | F86: Rendimentos | G86: Poupança | J86: Pago | Q86: exemplo | R86: 2026-10-17T12:00:00Z | S86: 2026-10-17T12:00:00Z | U86: 1
A87: 50e98d6d-6779-082c-ecbc-053409bb1454 | B87: 46296 | C87: Despesa | D87: Curso de idiomas | E87: 189 | F87: Educação | G87: Conta corrente | J87: Pago | Q87: exemplo | R87: 2026-10-17T12:00:00Z | S87: 2026-10-17T12:00:00Z | U87: 1
A88: 2eb52387-ab9f-4430-d8ae-93fbd978673a | B88: 46297 | C88: Despesa | D88: Mercado | E88: 412.8 | F88: Mercado | G88: Cartão de crédito | J88: Pendente | P88: 46323 | Q88: exemplo | R88: 2026-10-17T12:00:00Z | S88: 2026-10-17T12:00:00Z | U88: 1
A89: 47cd07f7-b74c-990a-9eeb-ba4e1c14df92 | B89: 46298 | C89: Despesa | D89: Padaria | E89: 24.5 | F89: Alimentação | G89: Carteira | J89: Pago | Q89: exemplo | R89: 2026-10-17T12:00:00Z | S89: 2026-10-17T12:00:00Z | U89: 1
A90: 5497db67-a54b-3b83-7440-cabee0ed4a62 | B90: 46298 | C90: Despesa | D90: Streaming de vídeo | E90: 55.9 | F90: Assinaturas | G90: Cartão de crédito | J90: Pendente | P90: 46323 | Q90: exemplo | R90: 2026-10-17T12:00:00Z | S90: 2026-10-17T12:00:00Z | U90: 1
A91: d563d56d-c887-417c-8b89-0fec6872d96b | B91: 46299 | C91: Despesa | D91: Streaming de música | E91: 21.9 | F91: Assinaturas | G91: Cartão de crédito | J91: Pendente | P91: 46323 | Q91: exemplo | R91: 2026-10-17T12:00:00Z | S91: 2026-10-17T12:00:00Z | U91: 1
A92: 2950e9ae-5089-be3b-ee8b-9e7c4a815857 | B92: 46299 | C92: Despesa | D92: Transporte por app | E92: 28.4 | F92: Transporte | G92: Cartão de crédito | J92: Pendente | P92: 46323 | Q92: exemplo | R92: 2026-10-17T12:00:00Z | S92: 2026-10-17T12:00:00Z | U92: 1
A93: ffce6973-7f62-df26-76c3-266043710baf | B93: 46300 | C93: Despesa | D93: Aluguel | E93: 2100 | F93: Moradia | G93: Conta corrente | J93: Pago | Q93: exemplo | R93: 2026-10-17T12:00:00Z | S93: 2026-10-17T12:00:00Z | U93: 1
A94: 62186f4b-1422-fbef-de38-42616a01977b | B94: 46300 | C94: Receita | D94: Salário | E94: 6200 | F94: Salário | G94: Conta corrente | J94: Pago | Q94: exemplo | R94: 2026-10-17T12:00:00Z | S94: 2026-10-17T12:00:00Z | U94: 1
A95: 4f56d48f-05e1-ddfb-3c37-bb0118b0f10e | B95: 46301 | C95: Despesa | D95: Combustível | E95: 224 | F95: Transporte | G95: Conta corrente | J95: Pago | Q95: exemplo | R95: 2026-10-17T12:00:00Z | S95: 2026-10-17T12:00:00Z | U95: 1
A96: 44a23f65-9015-b7c2-4b71-779491e0b539 | B96: 46301 | C96: Despesa | D96: Padaria | E96: 31 | F96: Alimentação | G96: Conta corrente | J96: Pago | Q96: exemplo | R96: 2026-10-17T12:00:00Z | S96: 2026-10-17T12:00:00Z | U96: 1
A97: dc7e351e-5fc8-16f4-afbc-11c41e93a2fb | B97: 46301 | C97: Transferência | D97: Reserva mensal | E97: 1000 | G97: Conta corrente | H97: Poupança | J97: Pago | Q97: exemplo | R97: 2026-10-17T12:00:00Z | S97: 2026-10-17T12:00:00Z | U97: 1
A98: a55c9c8e-2f7c-9cc7-cd64-a752b8ec796e | B98: 46302 | C98: Despesa | D98: Restaurante | E98: 96 | F98: Alimentação | G98: Cartão de crédito | J98: Pendente | P98: 46323 | Q98: exemplo | R98: 2026-10-17T12:00:00Z | S98: 2026-10-17T12:00:00Z | U98: 1
A99: 2cb8cefc-5814-b53f-2fec-42754e0e8896 | B99: 46302 | C99: Receita | D99: Salário | E99: 4800 | F99: Salário | G99: Conta corrente | J99: Pago | Q99: exemplo | R99: 2026-10-17T12:00:00Z | S99: 2026-10-17T12:00:00Z | U99: 1
A100: 36de6548-d90e-013a-1835-7aebd0ef5c36 | B100: 46303 | C100: Despesa | D100: Plano de saúde | E100: 520 | F100: Saúde | G100: Conta corrente | J100: Pago | Q100: exemplo | R100: 2026-10-17T12:00:00Z | S100: 2026-10-17T12:00:00Z | U100: 1
...

Sheet Contas
A1: id | B1: nome | C1: tipo | D1: titular | E1: saldo_inicial | F1: limite | G1: dia_fechamento | H1: dia_vencimento | I1: ordem | J1: arquivada | K1: criado_em | L1: atualizado_em | M1: rev
A2: d95bafc8-f2a4-d27b-dcf4-bb99f4bea973 | B2: Conta corrente | C2: Conta corrente | E2: 3500 | I2: 1 | K2: 2026-10-17T12:00:00Z | L2: 2026-10-17T12:00:00Z | M2: 1
A3: 21636369-8b52-9b4a-97b7-50923ceb3ffd | B3: Poupança | C3: Poupança | E3: 8000 | I3: 2 | K3: 2026-10-17T12:00:00Z | L3: 2026-10-17T12:00:00Z | M3: 1
A4: b8a1abcd-1a69-16c7-4da4-f9fc3c6da5d7 | B4: Carteira | C4: Carteira | E4: 150 | I4: 3 | K4: 2026-10-17T12:00:00Z | L4: 2026-10-17T12:00:00Z | M4: 1
A5: 5bc8fbbc-bde5-c099-4164-d8399f767c45 | B5: Investimentos | C5: Investimentos | E5: 12000 | I5: 4 | K5: 2026-10-17T12:00:00Z | L5: 2026-10-17T12:00:00Z | M5: 1
A6: 14a03569-d26b-9496-92e5-dfe8cb1855fe | B6: Cartão de crédito | C6: Cartão de crédito | E6: -1850 | F6: 6000 | G6: 20 | H6: 28 | I6: 5 | K6: 2026-10-17T12:00:00Z | L6: 2026-10-17T12:00:00Z | M6: 1

Sheet Categorias
A1: id | B1: nome | C1: tipo | D1: icone | E1: cor | F1: ordem | G1: arquivada | H1: criado_em | I1: atualizado_em | J1: rev
A2: 5bb58492-9daf-e6be-ad21-914625ee8c4c | B2: Alimentação | C2: Despesa | F2: 1 | H2: 2026-10-17T12:00:00Z | I2: 2026-10-17T12:00:00Z | J2: 1
A3: ef2843ff-74cf-f6a6-b6dc-0914faa30751 | B3: Mercado | C3: Despesa | F3: 2 | H3: 2026-10-17T12:00:00Z | I3: 2026-10-17T12:00:00Z | J3: 1
A4: 32a7cae9-df32-7560-0500-2635f5bffffb | B4: Moradia | C4: Despesa | F4: 3 | H4: 2026-10-17T12:00:00Z | I4: 2026-10-17T12:00:00Z | J4: 1
A5: 94aa3bff-595f-d6ff-9761-1f4ee0cb1e6b | B5: Contas e serviços | C5: Despesa | F5: 4 | H5: 2026-10-17T12:00:00Z | I5: 2026-10-17T12:00:00Z | J5: 1
A6: 7aaf4542-e6ae-fc3c-fa6b-b9c4b5ef5e70 | B6: Transporte | C6: Despesa | F6: 5 | H6: 2026-10-17T12:00:00Z | I6: 2026-10-17T12:00:00Z | J6: 1
A7: c42e1ca0-94cf-6aba-9eab-cba13f19711e | B7: Saúde | C7: Despesa | F7: 6 | H7: 2026-10-17T12:00:00Z | I7: 2026-10-17T12:00:00Z | J7: 1
A8: 15bf60ec-d0cd-69f3-b71e-45122169c619 | B8: Educação | C8: Despesa | F8: 7 | H8: 2026-10-17T12:00:00Z | I8: 2026-10-17T12:00:00Z | J8: 1
A9: 733611da-7593-4e8d-3aa0-c8cd4792c102 | B9: Lazer | C9: Despesa | F9: 8 | H9: 2026-10-17T12:00:00Z | I9: 2026-10-17T12:00:00Z | J9: 1
A10: cb6e16b3-6356-3e6e-fdae-c44eef2bcaab | B10: Assinaturas | C10: Despesa | F10: 9 | H10: 2026-10-17T12:00:00Z | I10: 2026-10-17T12:00:00Z | J10: 1
A11: ebd05eb7-3677-a4a5-f2df-6035d3c17334 | B11: Vestuário | C11: Despesa | F11: 10 | H11: 2026-10-17T12:00:00Z | I11: 2026-10-17T12:00:00Z | J11: 1
A12: 946dd889-aa84-b6d2-d53d-50bd7b32fabb | B12: Cuidados pessoais | C12: Despesa | F12: 11 | H12: 2026-10-17T12:00:00Z | I12: 2026-10-17T12:00:00Z | J12: 1
A13: cfd8984b-de1c-372f-a763-7e0807d27934 | B13: Outros | C13: Despesa | F13: 12 | H13: 2026-10-17T12:00:00Z | I13: 2026-10-17T12:00:00Z | J13: 1
... A18: 4fea6a7a-2eba-d8d7-a1c4-84b3b602ef1b | B18: Outras receitas | C18: Receita | F18: 17 | H18: 2026-10-17T12:00:00Z | I18: 2026-10-17T12:00:00Z | J18: 1

Sheet Orçamentos
A1: id | B1: categoria | C1: limite_mensal | D1: atualizado_em | E1: rev
A2: de404e1c-89fd-1b3f-8eb7-ae2ff7179bf4 | B2: Mercado | C2: 1800 | D2: 2026-10-17T12:00:00Z | E2: 1
A3: bd8ec9a1-f803-85ed-3d7c-9ec7081ab44d | B3: Alimentação | C3: 600 | D3: 2026-10-17T12:00:00Z | E3: 1
A4: 80abdcc1-6d49-8f3d-350d-aad92245d358 | B4: Transporte | C4: 500 | D4: 2026-10-17T12:00:00Z | E4: 1
A5: 640c93b5-910a-d452-9323-f6a62ebe4832 | B5: Lazer | C5: 300 | D5: 2026-10-17T12:00:00Z | E5: 1
A6: c9b5dfe5-865a-86bb-eaab-ef5c6e09ff05 | B6: Assinaturas | C6: 100 | D6: 2026-10-17T12:00:00Z | E6: 1
A7: c3db2246-4cf5-3186-82be-5d12a34268c7 | B7: Saúde | C7: 400 | D7: 2026-10-17T12:00:00Z | E7: 1
A8: 662e6120-f781-06fa-25ec-e01b2ff83173 | B8: Vestuário | C8: 250 | D8: 2026-10-17T12:00:00Z | E8: 1
A9: 220277ed-001b-ea0f-4c16-8ced103e1e0f | B9: Contas e serviços | C9: 450 | D9: 2026-10-17T12:00:00Z | E9: 1

Sheet Perfil
A1: campo | B1: valor
A2: nome | B2: Ana
A3: sexo
A4: data_nascimento

Sheet Metadados
A1: chave | B1: valor
A2: schema_version | B2: 1
A3: modelo_versao | B3: 1.3.0
A4: tipo_planilha | B4: individual
A5: nome_do_espaco | B5: Pessoal
A6: dados_de_exemplo | B6: sim
A7: revisao_global | B7: 0
A8: criado_em | B8: 2026-10-17T12:00:00Z
A9: aviso | B9: Não renomeie abas nem cabeçalhos. Veja a aba Leia-me.

Sheet Leia-me
B2: Orange Finance · como esta planilha funciona
B4: O que é | C4: Planilha criada pelo app Orange Finance. A aba Lançamentos guarda todos os lançamentos; o Dashboard mostra tudo por fórmulas e funciona mesmo sem o app.
B5: Tipo de planilha | C5: INDIVIDUAL: pertence só a você. Para compartilhar finanças com a família, crie um espaço compartilhado no app (gera outra planilha).
B6: Dados de exemplo | C6: As linhas com origem = exemplo são fictícias, só para você ver o painel funcionando. Apague-as antes de usar (o app gera a planilha vazia).
B7: Dashboard | C7: Edite apenas os filtros do topo (ano, mês, conta). Todo o resto é fórmula. Se uma fórmula for apagada, use Arquivo → Histórico de versões.
B8: Lançamentos | C8: Uma linha por lançamento. Valor sempre positivo; o tipo (Despesa, Receita, Transferência) define o sentido. Datas em formato de data. Status: Pago ou Pendente (para receitas, Pago = recebido).
B9: Cartão de crédito | C9: Compras no cartão usam a coluna ciclo_fatura (data de vencimento da fatura). O pagamento da fatura é uma Transferência da conta para o cartão.
B10: Exclusão | C10: Nunca apague linhas: preencha excluido_em com a data. Linhas com excluido_em preenchido são ignoradas pelo Dashboard.
B11: Colunas ocultas | C11: id, serie_id, parcela_n, parcelas_total, frequencia, ciclo_fatura, origem, criado_em, atualizado_em, excluido_em e rev são técnicas. Mostre-as pelo agrupamento de colunas apenas se precisar.
B12: Edições manuais | C12: Você pode editar valores na planilha. Ao editar, aumente o rev da linha e atualize atualizado_em para o app reconhecer a alteração (o app faz isso sozinho quando você edita por ele).
B13: Não faça | C13: Não renomeie abas nem cabeçalhos (linha 1), não reordene colunas, não insira colunas no meio, não use fórmulas nas abas de dados.
B14: Limite | C14: O Dashboard lê até a linha 20001 de Lançamentos (cerca de 20 mil lançamentos).
B15: Moeda e fuso | C15: Defina a localidade da planilha como Brasil e o fuso como America/Sao_Paulo (Arquivo → Configurações) para ver R$ 1.234,56 e datas corretas.

Sheet _Listas
A1: anos | B1: meses | C1: meses_abrev | D1: contas_filtro | E1: titulares_filtro | J1: categorias | K1: contas
A2: 2015 | B2: Janeiro | C2: Jan | D2: Todas | E2: Todos | J2: =IF(Categorias!$B$2="","",Categorias!$B$2) | K2: =IF(Contas!$B$2="","",Contas!$B$2)
A3: 2016 | B3: Fevereiro | C3: Fev | D3: =IF(Contas!$B$2="","",Contas!$B$2) | J3: =IF(Categorias!$B$3="","",Categorias!$B$3) | K3: =IF(Contas!$B$3="","",Contas!$B$3)
A4: 2017 | B4: Março | C4: Mar | D4: =IF(Contas!$B$3="","",Contas!$B$3) | J4: =IF(Categorias!$B$4="","",Categorias!$B$4) | K4: =IF(Contas!$B$4="","",Contas!$B$4)
A5: 2018 | B5: Abril | C5: Abr | D5: =IF(Contas!$B$4="","",Contas!$B$4) | J5: =IF(Categorias!$B$5="","",Categorias!$B$5) | K5: =IF(Contas!$B$5="","",Contas!$B$5)
A6: 2019 | B6: Maio | C6: Mai | D6: =IF(Contas!$B$5="","",Contas!$B$5) | J6: =IF(Categorias!$B$6="","",Categorias!$B$6) | K6: =IF(Contas!$B$6="","",Contas!$B$6)
A7: 2020 | B7: Junho | C7: Jun | D7: =IF(Contas!$B$6="","",Contas!$B$6) | J7: =IF(Categorias!$B$7="","",Categorias!$B$7) | K7: =IF(Contas!$B$7="","",Contas!$B$7)
A8: 2021 | B8: Julho | C8: Jul | D8: =IF(Contas!$B$7="","",Contas!$B$7) | J8: =IF(Categorias!$B$8="","",Categorias!$B$8) | K8: =IF(Contas!$B$8="","",Contas!$B$8)
A9: 2022 | B9: Agosto | C9: Ago | D9: =IF(Contas!$B$8="","",Contas!$B$8) | J9: =IF(Categorias!$B$9="","",Categorias!$B$9) | K9: =IF(Contas!$B$9="","",Contas!$B$9)
A10: 2023 | B10: Setembro | C10: Set | D10: =IF(Contas!$B$9="","",Contas!$B$9) | J10: =IF(Categorias!$B$10="","",Categorias!$B$10) | K10: =IF(Contas!$B$10="","",Contas!$B$10)
A11: 2024 | B11: Outubro | C11: Out | D11: =IF(Contas!$B$10="","",Contas!$B$10) | J11: =IF(Categorias!$B$11="","",Categorias!$B$11) | K11: =IF(Contas!$B$11="","",Contas!$B$11)
A12: 2025 | B12: Novembro | C12: Nov | D12: =IF(Contas!$B$11="","",Contas!$B$11) | J12: =IF(Categorias!$B$12="","",Categorias!$B$12) | K12: =IF(Contas!$B$12="","",Contas!$B$12)
A13: 2026 | B13: Dezembro | C13: Dez | D13: =IF(Contas!$B$12="","",Contas!$B$12) | J13: =IF(Categorias!$B$13="","",Categorias!$B$13) | K13: =IF(Contas!$B$13="","",Contas!$B$13)
A14: 2027 | D14: =IF(Contas!$B$13="","",Contas!$B$13) | J14: =IF(Categorias!$B$14="","",Categorias!$B$14)
A15: 2028 | J15: =IF(Categorias!$B$15="","",Categorias!$B$15)
A16: 2029 | J16: =IF(Categorias!$B$16="","",Categorias!$B$16)
A17: 2030 | J17: =IF(Categorias!$B$17="","",Categorias!$B$17)
A18: 2031 | J18: =IF(Categorias!$B$18="","",Categorias!$B$18)
A19: 2032 | J19: =IF(Categorias!$B$19="","",Categorias!$B$19)
A20: 2033 | J20: =IF(Categorias!$B$20="","",Categorias!$B$20)
A21: 2034 | J21: =IF(Categorias!$B$21="","",Categorias!$B$21)
A22: 2035 | J22: =IF(Categorias!$B$22="","",Categorias!$B$22)
A23: 2036 | J23: =IF(Categorias!$B$23="","",Categorias!$B$23)
A24: 2037 | J24: =IF(Categorias!$B$24="","",Categorias!$B$24)
A25: 2038 | J25: =IF(Categorias!$B$25="","",Categorias!$B$25)
A26: 2039 | J26: =IF(Categorias!$B$26="","",Categorias!$B$26)
A27: 2040 | J27: =IF(Categorias!$B$27="","",Categorias!$B$27)
J28: =IF(Categorias!$B$28="","",Categorias!$B$28)
J29: =IF(Categorias!$B$29="","",Categorias!$B$29)
J30: =IF(Categorias!$B$30="","",Categorias!$B$30)
J31: =IF(Categorias!$B$31="","",Categorias!$B$31)
J32: =IF(Categorias!$B$32="","",Categorias!$B$32)
J33: =IF(Categorias!$B$33="","",Categorias!$B$33)
J34: =IF(Categorias!$B$34="","",Categorias!$B$34)
J35: =IF(Categorias!$B$35="","",Categorias!$B$35)
J36: =IF(Categorias!$B$36="","",Categorias!$B$36)
J37: =IF(Categorias!$B$37="","",Categorias!$B$37)
J38: =IF(Categorias!$B$38="","",Categorias!$B$38)
J39: =IF(Categorias!$B$39="","",Categorias!$B$39)
J40: =IF(Categorias!$B$40="","",Categorias!$B$40)
J41: =IF(Categorias!$B$41="","",Categorias!$B$41)
J42: =IF(Categorias!$B$42="","",Categorias!$B$42)

Sheet _Calc
A1: PARÂMETROS (alimentados pelos filtros do Dashboard) | D1: KPIs
A2: ano | B2: =Dashboard!$B$6 | D2: rec_mes | E2: =SUMIFS(L_VALOR,L_TIPO,"Receita",L_DATA,">="&F_INI,L_DATA,"<="&F_FIM,L_CONTA,F_CONTA,L_TIT,F_TIT,L_EXCL,"")
A3: mes_num | B3: =MATCH(Dashboard!$D$6,'_Listas'!$B$2:$B$13,0) | D3: desp_mes | E3: =SUMIFS(L_VALOR,L_TIPO,"Despesa",L_DATA,">="&F_INI,L_DATA,"<="&F_FIM,L_CONTA,F_CONTA,L_TIT,F_TIT,L_EXCL,"")
A4: inicio | B4: =DATE(B2,B3,1) | D4: rec_ant | E4: =SUMIFS(L_VALOR,L_TIPO,"Receita",L_DATA,">="&F_INI_ANT,L_DATA,"<="&F_FIM_ANT,L_CONTA,F_CONTA,L_TIT,F_TIT,L_EXCL,"")
A5: fim | B5: =EOMONTH(B4,0) | D5: desp_ant | E5: =SUMIFS(L_VALOR,L_TIPO,"Despesa",L_DATA,">="&F_INI_ANT,L_DATA,"<="&F_FIM_ANT,L_CONTA,F_CONTA,L_TIT,F_TIT,L_EXCL,"")
A6: inicio_ant | B6: =EDATE(B4,-1) | D6: a_pagar_mes | E6: =SUMPRODUCT((L_TIPO="Despesa")*(L_STATUS="Pendente")*(L_EXCL="")*(((L_CONTA=F_CONTA_SEL)+(F_CONTA_SEL="Todas"))>0)*(((L_TIT=F_TIT_SEL)+(F_TIT_SEL="Todos"))>0)*((L_DATA*(L_CICLO=0)+L_CICLO)>=F_INI)*((L_DATA*(L_CICLO=0)+L_CICLO)<=F_FIM)*L_VALOR)
A7: fim_ant | B7: =EOMONTH(B6,0) | D7: atrasadas_valor | E7: =SUMPRODUCT((L_TIPO="Despesa")*(L_STATUS="Pendente")*(L_EXCL="")*(((L_CONTA=F_CONTA_SEL)+(F_CONTA_SEL="Todas"))>0)*(((L_TIT=F_TIT_SEL)+(F_TIT_SEL="Todos"))>0)*((L_DATA*(L_CICLO=0)+L_CICLO)>0)*((L_DATA*(L_CICLO=0)+L_CICLO)<HOJE)*L_VALOR)
A8: conta_sel | B8: =Dashboard!$F$6 | D8: atrasadas_qtd | E8: =SUMPRODUCT((L_TIPO="Despesa")*(L_STATUS="Pendente")*(L_EXCL="")*(((L_CONTA=F_CONTA_SEL)+(F_CONTA_SEL="Todas"))>0)*(((L_TIT=F_TIT_SEL)+(F_TIT_SEL="Todos"))>0)*((L_DATA*(L_CICLO=0)+L_CICLO)>0)*((L_DATA*(L_CICLO=0)+L_CICLO)<HOJE))
A9: crit_conta | B9: =IF(B8="Todas","<>#sem#",B8) | D9: saldo_contas | E9: =SUMIFS(D160:D171,B160:B171,"<>Cartão de crédito")
A10: crit_titular | B10: ="<>#sem#" | D10: divida_cartoes | E10: =MAX(0,-SUMIFS(D160:D171,B160:B171,"Cartão de crédito"))
A11: hoje | B11: =TODAY() | D11: maior_cat_nome | E11: =L15
A12: titular_sel | B12: ="Todos" | D12: maior_cat_valor | E12: =M15
A13: CATEGORIAS DE DESPESA (mês filtrado)
A14: nome | B14: tipo | C14: total_mes | D14: total_ant | E14: chave_total | F14: variacao | G14: chave_variacao | I14: rank | J14: chave | K14: idx | L14: categoria | M14: total | N14: pct_total | O14: anterior | Q14: rank | R14: chave | S14: idx | T14: categoria | U14: anterior | V14: atual | W14: delta | X14: delta_pct
A15: =IF(Categorias!$B$2="","",Categorias!$B$2) | B15: =IF(A15="","",Categorias!$C$2) | C15: =IF(B15="Despesa",SUMIFS(L_VALOR,L_TIPO,"Despesa",L_DATA,">="&F_INI,L_DATA,"<="&F_FIM,L_CONTA,F_CONTA,L_TIT,F_TIT,L_EXCL,"",L_CAT,A15),0) | D15: =IF(B15="Despesa",SUMIFS(L_VALOR,L_TIPO,"Despesa",L_DATA,">="&F_INI_ANT,L_DATA,"<="&F_FIM_ANT,L_CONTA,F_CONTA,L_TIT,F_TIT,L_EXCL,"",L_CAT,A15),0) | E15: =IF(C15>0.004,C15+ROW()/10^7,0) | F15: =C15-D15 | G15: =IF(F15>0.004,F15+ROW()/10^7,0) | I15: 1 | J15: =LARGE($E$15:$E$55,I15) | K15: =IF(J15>0,MATCH(J15,$E$15:$E$55,0),0) | L15: =IF(K15>0,INDEX($A$15:$A$55,K15),"") | M15: =IF(K15>0,INDEX($C$15:$C$55,K15),0) | N15: =IF($E$3>0,M15/$E$3,0) | O15: =IF(K15>0,INDEX($D$15:$D$55,K15),0) | Q15: 1 | R15: =LARGE($G$15:$G$55,Q15) | S15: =IF(R15>0,MATCH(R15,$G$15:$G$55,0),0) | T15: =IF(S15>0,INDEX($A$15:$A$55,S15),"") | U15: =IF(S15>0,INDEX($D$15:$D$55,S15),0) | V15: =IF(S15>0,INDEX($C$15:$C$55,S15),0) | W15: =V15-U15 | X15: =IF(S15=0,"",IF(U15>0,W15/U15,"novo"))
A16: =IF(Categorias!$B$3="","",Categorias!$B$3) | B16: =IF(A16="","",Categorias!$C$3) | C16: =IF(B16="Despesa",SUMIFS(L_VALOR,L_TIPO,"Despesa",L_DATA,">="&F_INI,L_DATA,"<="&F_FIM,L_CONTA,F_CONTA,L_TIT,F_TIT,L_EXCL,"",L_CAT,A16),0) | D16: =IF(B16="Despesa",SUMIFS(L_VALOR,L_TIPO,"Despesa",L_DATA,">="&F_INI_ANT,L_DATA,"<="&F_FIM_ANT,L_CONTA,F_CONTA,L_TIT,F_TIT,L_EXCL,"",L_CAT,A16),0) | E16: =IF(C16>0.004,C16+ROW()/10^7,0) | F16: =C16-D16 | G16: =IF(F16>0.004,F16+ROW()/10^7,0) | I16: 2 | J16: =LARGE($E$15:$E$55,I16) | K16: =IF(J16>0,MATCH(J16,$E$15:$E$55,0),0) | L16: =IF(K16>0,INDEX($A$15:$A$55,K16),"") | M16: =IF(K16>0,INDEX($C$15:$C$55,K16),0) | N16: =IF($E$3>0,M16/$E$3,0) | O16: =IF(K16>0,INDEX($D$15:$D$55,K16),0) | Q16: 2 | R16: =LARGE($G$15:$G$55,Q16) | S16: =IF(R16>0,MATCH(R16,$G$15:$G$55,0),0) | T16: =IF(S16>0,INDEX($A$15:$A$55,S16),"") | U16: =IF(S16>0,INDEX($D$15:$D$55,S16),0) | V16: =IF(S16>0,INDEX($C$15:$C$55,S16),0) | W16: =V16-U16 | X16: =IF(S16=0,"",IF(U16>0,W16/U16,"novo"))
A17: =IF(Categorias!$B$4="","",Categorias!$B$4) | B17: =IF(A17="","",Categorias!$C$4) | C17: =IF(B17="Despesa",SUMIFS(L_VALOR,L_TIPO,"Despesa",L_DATA,">="&F_INI,L_DATA,"<="&F_FIM,L_CONTA,F_CONTA,L_TIT,F_TIT,L_EXCL,"",L_CAT,A17),0) | D17: =IF(B17="Despesa",SUMIFS(L_VALOR,L_TIPO,"Despesa",L_DATA,">="&F_INI_ANT,L_DATA,"<="&F_FIM_ANT,L_CONTA,F_CONTA,L_TIT,F_TIT,L_EXCL,"",L_CAT,A17),0) | E17: =IF(C17>0.004,C17+ROW()/10^7,0) | F17: =C17-D17 | G17: =IF(F17>0.004,F17+ROW()/10^7,0) | I17: 3 | J17: =LARGE($E$15:$E$55,I17) | K17: =IF(J17>0,MATCH(J17,$E$15:$E$55,0),0) | L17: =IF(K17>0,INDEX($A$15:$A$55,K17),"") | M17: =IF(K17>0,INDEX($C$15:$C$55,K17),0) | N17: =IF($E$3>0,M17/$E$3,0) | O17: =IF(K17>0,INDEX($D$15:$D$55,K17),0) | Q17: 3 | R17: =LARGE($G$15:$G$55,Q17) | S17: =IF(R17>0,MATCH(R17,$G$15:$G$55,0),0) | T17: =IF(S17>0,INDEX($A$15:$A$55,S17),"") | U17: =IF(S17>0,INDEX($D$15:$D$55,S17),0) | V17: =IF(S17>0,INDEX($C$15:$C$55,S17),0) | W17: =V17-U17 | X17: =IF(S17=0,"",IF(U17>0,W17/U17,"novo"))
A18: =IF(Categorias!$B$5="","",Categorias!$B$5) | B18: =IF(A18="","",Categorias!$C$5) | C18: =IF(B18="Despesa",SUMIFS(L_VALOR,L_TIPO,"Despesa",L_DATA,">="&F_INI,L_DATA,"<="&F_FIM,L_CONTA,F_CONTA,L_TIT,F_TIT,L_EXCL,"",L_CAT,A18),0) | D18: =IF(B18="Despesa",SUMIFS(L_VALOR,L_TIPO,"Despesa",L_DATA,">="&F_INI_ANT,L_DATA,"<="&F_FIM_ANT,L_CONTA,F_CONTA,L_TIT,F_TIT,L_EXCL,"",L_CAT,A18),0) | E18: =IF(C18>0.004,C18+ROW()/10^7,0) | F18: =C18-D18 | G18: =IF(F18>0.004,F18+ROW()/10^7,0) | I18: 4 | J18: =LARGE($E$15:$E$55,I18) | K18: =IF(J18>0,MATCH(J18,$E$15:$E$55,0),0) | L18: =IF(K18>0,INDEX($A$15:$A$55,K18),"") | M18: =IF(K18>0,INDEX($C$15:$C$55,K18),0) | N18: =IF($E$3>0,M18/$E$3,0) | O18: =IF(K18>0,INDEX($D$15:$D$55,K18),0) | Q18: 4 | R18: =LARGE($G$15:$G$55,Q18) | S18: =IF(R18>0,MATCH(R18,$G$15:$G$55,0),0) | T18: =IF(S18>0,INDEX($A$15:$A$55,S18),"") | U18: =IF(S18>0,INDEX($D$15:$D$55,S18),0) | V18: =IF(S18>0,INDEX($C$15:$C$55,S18),0) | W18: =V18-U18 | X18: =IF(S18=0,"",IF(U18>0,W18/U18,"novo"))
A19: =IF(Categorias!$B$6="","",Categorias!$B$6) | B19: =IF(A19="","",Categorias!$C$6) | C19: =IF(B19="Despesa",SUMIFS(L_VALOR,L_TIPO,"Despesa",L_DATA,">="&F_INI,L_DATA,"<="&F_FIM,L_CONTA,F_CONTA,L_TIT,F_TIT,L_EXCL,"",L_CAT,A19),0) | D19: =IF(B19="Despesa",SUMIFS(L_VALOR,L_TIPO,"Despesa",L_DATA,">="&F_INI_ANT,L_DATA,"<="&F_FIM_ANT,L_CONTA,F_CONTA,L_TIT,F_TIT,L_EXCL,"",L_CAT,A19),0) | E19: =IF(C19>0.004,C19+ROW()/10^7,0) | F19: =C19-D19 | G19: =IF(F19>0.004,F19+ROW()/10^7,0) | I19: 5 | J19: =LARGE($E$15:$E$55,I19) | K19: =IF(J19>0,MATCH(J19,$E$15:$E$55,0),0) | L19: =IF(K19>0,INDEX($A$15:$A$55,K19),"") | M19: =IF(K19>0,INDEX($C$15:$C$55,K19),0) | N19: =IF($E$3>0,M19/$E$3,0) | O19: =IF(K19>0,INDEX($D$15:$D$55,K19),0) | Q19: 5 | R19: =LARGE($G$15:$G$55,Q19) | S19: =IF(R19>0,MATCH(R19,$G$15:$G$55,0),0) | T19: =IF(S19>0,INDEX($A$15:$A$55,S19),"") | U19: =IF(S19>0,INDEX($D$15:$D$55,S19),0) | V19: =IF(S19>0,INDEX($C$15:$C$55,S19),0) | W19: =V19-U19 | X19: =IF(S19=0,"",IF(U19>0,W19/U19,"novo"))
A20: =IF(Categorias!$B$7="","",Categorias!$B$7) | B20: =IF(A20="","",Categorias!$C$7) | C20: =IF(B20="Despesa",SUMIFS(L_VALOR,L_TIPO,"Despesa",L_DATA,">="&F_INI,L_DATA,"<="&F_FIM,L_CONTA,F_CONTA,L_TIT,F_TIT,L_EXCL,"",L_CAT,A20),0) | D20: =IF(B20="Despesa",SUMIFS(L_VALOR,L_TIPO,"Despesa",L_DATA,">="&F_INI_ANT,L_DATA,"<="&F_FIM_ANT,L_CONTA,F_CONTA,L_TIT,F_TIT,L_EXCL,"",L_CAT,A20),0) | E20: =IF(C20>0.004,C20+ROW()/10^7,0) | F20: =C20-D20 | G20: =IF(F20>0.004,F20+ROW()/10^7,0) | I20: 6 | J20: =LARGE($E$15:$E$55,I20) | K20: =IF(J20>0,MATCH(J20,$E$15:$E$55,0),0) | L20: =IF(K20>0,INDEX($A$15:$A$55,K20),"") | M20: =IF(K20>0,INDEX($C$15:$C$55,K20),0) | N20: =IF($E$3>0,M20/$E$3,0) | O20: =IF(K20>0,INDEX($D$15:$D$55,K20),0)
A21: =IF(Categorias!$B$8="","",Categorias!$B$8) | B21: =IF(A21="","",Categorias!$C$8) | C21: =IF(B21="Despesa",SUMIFS(L_VALOR,L_TIPO,"Despesa",L_DATA,">="&F_INI,L_DATA,"<="&F_FIM,L_CONTA,F_CONTA,L_TIT,F_TIT,L_EXCL,"",L_CAT,A21),0) | D21: =IF(B21="Despesa",SUMIFS(L_VALOR,L_TIPO,"Despesa",L_DATA,">="&F_INI_ANT,L_DATA,"<="&F_FIM_ANT,L_CONTA,F_CONTA,L_TIT,F_TIT,L_EXCL,"",L_CAT,A21),0) | E21: =IF(C21>0.004,C21+ROW()/10^7,0) | F21: =C21-D21 | G21: =IF(F21>0.004,F21+ROW()/10^7,0) | I21: 7 | J21: =LARGE($E$15:$E$55,I21) | K21: =IF(J21>0,MATCH(J21,$E$15:$E$55,0),0) | L21: =IF(K21>0,INDEX($A$15:$A$55,K21),"") | M21: =IF(K21>0,INDEX($C$15:$C$55,K21),0) | N21: =IF($E$3>0,M21/$E$3,0) | O21: =IF(K21>0,INDEX($D$15:$D$55,K21),0)
A22: =IF(Categorias!$B$9="","",Categorias!$B$9) | B22: =IF(A22="","",Categorias!$C$9) | C22: =IF(B22="Despesa",SUMIFS(L_VALOR,L_TIPO,"Despesa",L_DATA,">="&F_INI,L_DATA,"<="&F_FIM,L_CONTA,F_CONTA,L_TIT,F_TIT,L_EXCL,"",L_CAT,A22),0) | D22: =IF(B22="Despesa",SUMIFS(L_VALOR,L_TIPO,"Despesa",L_DATA,">="&F_INI_ANT,L_DATA,"<="&F_FIM_ANT,L_CONTA,F_CONTA,L_TIT,F_TIT,L_EXCL,"",L_CAT,A22),0) | E22: =IF(C22>0.004,C22+ROW()/10^7,0) | F22: =C22-D22 | G22: =IF(F22>0.004,F22+ROW()/10^7,0) | I22: 8 | J22: =LARGE($E$15:$E$55,I22) | K22: =IF(J22>0,MATCH(J22,$E$15:$E$55,0),0) | L22: =IF(K22>0,INDEX($A$15:$A$55,K22),"") | M22: =IF(K22>0,INDEX($C$15:$C$55,K22),0) | N22: =IF($E$3>0,M22/$E$3,0) | O22: =IF(K22>0,INDEX($D$15:$D$55,K22),0)
A23: =IF(Categorias!$B$10="","",Categorias!$B$10) | B23: =IF(A23="","",Categorias!$C$10) | C23: =IF(B23="Despesa",SUMIFS(L_VALOR,L_TIPO,"Despesa",L_DATA,">="&F_INI,L_DATA,"<="&F_FIM,L_CONTA,F_CONTA,L_TIT,F_TIT,L_EXCL,"",L_CAT,A23),0) | D23: =IF(B23="Despesa",SUMIFS(L_VALOR,L_TIPO,"Despesa",L_DATA,">="&F_INI_ANT,L_DATA,"<="&F_FIM_ANT,L_CONTA,F_CONTA,L_TIT,F_TIT,L_EXCL,"",L_CAT,A23),0) | E23: =IF(C23>0.004,C23+ROW()/10^7,0) | F23: =C23-D23 | G23: =IF(F23>0.004,F23+ROW()/10^7,0) | I23: 9 | J23: =LARGE($E$15:$E$55,I23) | K23: =IF(J23>0,MATCH(J23,$E$15:$E$55,0),0) | L23: =IF(K23>0,INDEX($A$15:$A$55,K23),"") | M23: =IF(K23>0,INDEX($C$15:$C$55,K23),0) | N23: =IF($E$3>0,M23/$E$3,0) | O23: =IF(K23>0,INDEX($D$15:$D$55,K23),0)
A24: =IF(Categorias!$B$11="","",Categorias!$B$11) | B24: =IF(A24="","",Categorias!$C$11) | C24: =IF(B24="Despesa",SUMIFS(L_VALOR,L_TIPO,"Despesa",L_DATA,">="&F_INI,L_DATA,"<="&F_FIM,L_CONTA,F_CONTA,L_TIT,F_TIT,L_EXCL,"",L_CAT,A24),0) | D24: =IF(B24="Despesa",SUMIFS(L_VALOR,L_TIPO,"Despesa",L_DATA,">="&F_INI_ANT,L_DATA,"<="&F_FIM_ANT,L_CONTA,F_CONTA,L_TIT,F_TIT,L_EXCL,"",L_CAT,A24),0) | E24: =IF(C24>0.004,C24+ROW()/10^7,0) | F24: =C24-D24 | G24: =IF(F24>0.004,F24+ROW()/10^7,0) | I24: 10 | J24: =LARGE($E$15:$E$55,I24) | K24: =IF(J24>0,MATCH(J24,$E$15:$E$55,0),0) | L24: =IF(K24>0,INDEX($A$15:$A$55,K24),"") | M24: =IF(K24>0,INDEX($C$15:$C$55,K24),0) | N24: =IF($E$3>0,M24/$E$3,0) | O24: =IF(K24>0,INDEX($D$15:$D$55,K24),0)
A25: =IF(Categorias!$B$12="","",Categorias!$B$12) | B25: =IF(A25="","",Categorias!$C$12) | C25: =IF(B25="Despesa",SUMIFS(L_VALOR,L_TIPO,"Despesa",L_DATA,">="&F_INI,L_DATA,"<="&F_FIM,L_CONTA,F_CONTA,L_TIT,F_TIT,L_EXCL,"",L_CAT,A25),0) | D25: =IF(B25="Despesa",SUMIFS(L_VALOR,L_TIPO,"Despesa",L_DATA,">="&F_INI_ANT,L_DATA,"<="&F_FIM_ANT,L_CONTA,F_CONTA,L_TIT,F_TIT,L_EXCL,"",L_CAT,A25),0) | E25: =IF(C25>0.004,C25+ROW()/10^7,0) | F25: =C25-D25 | G25: =IF(F25>0.004,F25+ROW()/10^7,0)
A26: =IF(Categorias!$B$13="","",Categorias!$B$13) | B26: =IF(A26="","",Categorias!$C$13) | C26: =IF(B26="Despesa",SUMIFS(L_VALOR,L_TIPO,"Despesa",L_DATA,">="&F_INI,L_DATA,"<="&F_FIM,L_CONTA,F_CONTA,L_TIT,F_TIT,L_EXCL,"",L_CAT,A26),0) | D26: =IF(B26="Despesa",SUMIFS(L_VALOR,L_TIPO,"Despesa",L_DATA,">="&F_INI_ANT,L_DATA,"<="&F_FIM_ANT,L_CONTA,F_CONTA,L_TIT,F_TIT,L_EXCL,"",L_CAT,A26),0) | E26: =IF(C26>0.004,C26+ROW()/10^7,0) | F26: =C26-D26 | G26: =IF(F26>0.004,F26+ROW()/10^7,0)
A27: =IF(Categorias!$B$14="","",Categorias!$B$14) | B27: =IF(A27="","",Categorias!$C$14) | C27: =IF(B27="Despesa",SUMIFS(L_VALOR,L_TIPO,"Despesa",L_DATA,">="&F_INI,L_DATA,"<="&F_FIM,L_CONTA,F_CONTA,L_TIT,F_TIT,L_EXCL,"",L_CAT,A27),0) | D27: =IF(B27="Despesa",SUMIFS(L_VALOR,L_TIPO,"Despesa",L_DATA,">="&F_INI_ANT,L_DATA,"<="&F_FIM_ANT,L_CONTA,F_CONTA,L_TIT,F_TIT,L_EXCL,"",L_CAT,A27),0) | E27: =IF(C27>0.004,C27+ROW()/10^7,0) | F27: =C27-D27 | G27: =IF(F27>0.004,F27+ROW()/10^7,0)
A28: =IF(Categorias!$B$15="","",Categorias!$B$15) | B28: =IF(A28="","",Categorias!$C$15) | C28: =IF(B28="Despesa",SUMIFS(L_VALOR,L_TIPO,"Despesa",L_DATA,">="&F_INI,L_DATA,"<="&F_FIM,L_CONTA,F_CONTA,L_TIT,F_TIT,L_EXCL,"",L_CAT,A28),0) | D28: =IF(B28="Despesa",SUMIFS(L_VALOR,L_TIPO,"Despesa",L_DATA,">="&F_INI_ANT,L_DATA,"<="&F_FIM_ANT,L_CONTA,F_CONTA,L_TIT,F_TIT,L_EXCL,"",L_CAT,A28),0) | E28: =IF(C28>0.004,C28+ROW()/10^7,0) | F28: =C28-D28 | G28: =IF(F28>0.004,F28+ROW()/10^7,0)
A29: =IF(Categorias!$B$16="","",Categorias!$B$16) | B29: =IF(A29="","",Categorias!$C$16) | C29: =IF(B29="Despesa",SUMIFS(L_VALOR,L_TIPO,"Despesa",L_DATA,">="&F_INI,L_DATA,"<="&F_FIM,L_CONTA,F_CONTA,L_TIT,F_TIT,L_EXCL,"",L_CAT,A29),0) | D29: =IF(B29="Despesa",SUMIFS(L_VALOR,L_TIPO,"Despesa",L_DATA,">="&F_INI_ANT,L_DATA,"<="&F_FIM_ANT,L_CONTA,F_CONTA,L_TIT,F_TIT,L_EXCL,"",L_CAT,A29),0) | E29: =IF(C29>0.004,C29+ROW()/10^7,0) | F29: =C29-D29 | G29: =IF(F29>0.004,F29+ROW()/10^7,0)
A30: =IF(Categorias!$B$17="","",Categorias!$B$17) | B30: =IF(A30="","",Categorias!$C$17) | C30: =IF(B30="Despesa",SUMIFS(L_VALOR,L_TIPO,"Despesa",L_DATA,">="&F_INI,L_DATA,"<="&F_FIM,L_CONTA,F_CONTA,L_TIT,F_TIT,L_EXCL,"",L_CAT,A30),0) | D30: =IF(B30="Despesa",SUMIFS(L_VALOR,L_TIPO,"Despesa",L_DATA,">="&F_INI_ANT,L_DATA,"<="&F_FIM_ANT,L_CONTA,F_CONTA,L_TIT,F_TIT,L_EXCL,"",L_CAT,A30),0) | E30: =IF(C30>0.004,C30+ROW()/10^7,0) | F30: =C30-D30 | G30: =IF(F30>0.004,F30+ROW()/10^7,0)
A31: =IF(Categorias!$B$18="","",Categorias!$B$18) | B31: =IF(A31="","",Categorias!$C$18) | C31: =IF(B31="Despesa",SUMIFS(L_VALOR,L_TIPO,"Despesa",L_DATA,">="&F_INI,L_DATA,"<="&F_FIM,L_CONTA,F_CONTA,L_TIT,F_TIT,L_EXCL,"",L_CAT,A31),0) | D31: =IF(B31="Despesa",SUMIFS(L_VALOR,L_TIPO,"Despesa",L_DATA,">="&F_INI_ANT,L_DATA,"<="&F_FIM_ANT,L_CONTA,F_CONTA,L_TIT,F_TIT,L_EXCL,"",L_CAT,A31),0) | E31: =IF(C31>0.004,C31+ROW()/10^7,0) | F31: =C31-D31 | G31: =IF(F31>0.004,F31+ROW()/10^7,0)
A32: =IF(Categorias!$B$19="","",Categorias!$B$19) | B32: =IF(A32="","",Categorias!$C$19) | C32: =IF(B32="Despesa",SUMIFS(L_VALOR,L_TIPO,"Despesa",L_DATA,">="&F_INI,L_DATA,"<="&F_FIM,L_CONTA,F_CONTA,L_TIT,F_TIT,L_EXCL,"",L_CAT,A32),0) | D32: =IF(B32="Despesa",SUMIFS(L_VALOR,L_TIPO,"Despesa",L_DATA,">="&F_INI_ANT,L_DATA,"<="&F_FIM_ANT,L_CONTA,F_CONTA,L_TIT,F_TIT,L_EXCL,"",L_CAT,A32),0) | E32: =IF(C32>0.004,C32+ROW()/10^7,0) | F32: =C32-D32 | G32: =IF(F32>0.004,F32+ROW()/10^7,0)
A33: =IF(Categorias!$B$20="","",Categorias!$B$20) | B33: =IF(A33="","",Categorias!$C$20) | C33: =IF(B33="Despesa",SUMIFS(L_VALOR,L_TIPO,"Despesa",L_DATA,">="&F_INI,L_DATA,"<="&F_FIM,L_CONTA,F_CONTA,L_TIT,F_TIT,L_EXCL,"",L_CAT,A33),0) | D33: =IF(B33="Despesa",SUMIFS(L_VALOR,L_TIPO,"Despesa",L_DATA,">="&F_INI_ANT,L_DATA,"<="&F_FIM_ANT,L_CONTA,F_CONTA,L_TIT,F_TIT,L_EXCL,"",L_CAT,A33),0) | E33: =IF(C33>0.004,C33+ROW()/10^7,0) | F33: =C33-D33 | G33: =IF(F33>0.004,F33+ROW()/10^7,0)
A34: =IF(Categorias!$B$21="","",Categorias!$B$21) | B34: =IF(A34="","",Categorias!$C$21) | C34: =IF(B34="Despesa",SUMIFS(L_VALOR,L_TIPO,"Despesa",L_DATA,">="&F_INI,L_DATA,"<="&F_FIM,L_CONTA,F_CONTA,L_TIT,F_TIT,L_EXCL,"",L_CAT,A34),0) | D34: =IF(B34="Despesa",SUMIFS(L_VALOR,L_TIPO,"Despesa",L_DATA,">="&F_INI_ANT,L_DATA,"<="&F_FIM_ANT,L_CONTA,F_CONTA,L_TIT,F_TIT,L_EXCL,"",L_CAT,A34),0) | E34: =IF(C34>0.004,C34+ROW()/10^7,0) | F34: =C34-D34 | G34: =IF(F34>0.004,F34+ROW()/10^7,0)
A35: =IF(Categorias!$B$22="","",Categorias!$B$22) | B35: =IF(A35="","",Categorias!$C$22) | C35: =IF(B35="Despesa",SUMIFS(L_VALOR,L_TIPO,"Despesa",L_DATA,">="&F_INI,L_DATA,"<="&F_FIM,L_CONTA,F_CONTA,L_TIT,F_TIT,L_EXCL,"",L_CAT,A35),0) | D35: =IF(B35="Despesa",SUMIFS(L_VALOR,L_TIPO,"Despesa",L_DATA,">="&F_INI_ANT,L_DATA,"<="&F_FIM_ANT,L_CONTA,F_CONTA,L_TIT,F_TIT,L_EXCL,"",L_CAT,A35),0) | E35: =IF(C35>0.004,C35+ROW()/10^7,0) | F35: =C35-D35 | G35: =IF(F35>0.004,F35+ROW()/10^7,0)
A36: =IF(Categorias!$B$23="","",Categorias!$B$23) | B36: =IF(A36="","",Categorias!$C$23) | C36: =IF(B36="Despesa",SUMIFS(L_VALOR,L_TIPO,"Despesa",L_DATA,">="&F_INI,L_DATA,"<="&F_FIM,L_CONTA,F_CONTA,L_TIT,F_TIT,L_EXCL,"",L_CAT,A36),0) | D36: =IF(B36="Despesa",SUMIFS(L_VALOR,L_TIPO,"Despesa",L_DATA,">="&F_INI_ANT,L_DATA,"<="&F_FIM_ANT,L_CONTA,F_CONTA,L_TIT,F_TIT,L_EXCL,"",L_CAT,A36),0) | E36: =IF(C36>0.004,C36+ROW()/10^7,0) | F36: =C36-D36 | G36: =IF(F36>0.004,F36+ROW()/10^7,0)
A37: =IF(Categorias!$B$24="","",Categorias!$B$24) | B37: =IF(A37="","",Categorias!$C$24) | C37: =IF(B37="Despesa",SUMIFS(L_VALOR,L_TIPO,"Despesa",L_DATA,">="&F_INI,L_DATA,"<="&F_FIM,L_CONTA,F_CONTA,L_TIT,F_TIT,L_EXCL,"",L_CAT,A37),0) | D37: =IF(B37="Despesa",SUMIFS(L_VALOR,L_TIPO,"Despesa",L_DATA,">="&F_INI_ANT,L_DATA,"<="&F_FIM_ANT,L_CONTA,F_CONTA,L_TIT,F_TIT,L_EXCL,"",L_CAT,A37),0) | E37: =IF(C37>0.004,C37+ROW()/10^7,0) | F37: =C37-D37 | G37: =IF(F37>0.004,F37+ROW()/10^7,0)
A38: =IF(Categorias!$B$25="","",Categorias!$B$25) | B38: =IF(A38="","",Categorias!$C$25) | C38: =IF(B38="Despesa",SUMIFS(L_VALOR,L_TIPO,"Despesa",L_DATA,">="&F_INI,L_DATA,"<="&F_FIM,L_CONTA,F_CONTA,L_TIT,F_TIT,L_EXCL,"",L_CAT,A38),0) | D38: =IF(B38="Despesa",SUMIFS(L_VALOR,L_TIPO,"Despesa",L_DATA,">="&F_INI_ANT,L_DATA,"<="&F_FIM_ANT,L_CONTA,F_CONTA,L_TIT,F_TIT,L_EXCL,"",L_CAT,A38),0) | E38: =IF(C38>0.004,C38+ROW()/10^7,0) | F38: =C38-D38 | G38: =IF(F38>0.004,F38+ROW()/10^7,0)
A39: =IF(Categorias!$B$26="","",Categorias!$B$26) | B39: =IF(A39="","",Categorias!$C$26) | C39: =IF(B39="Despesa",SUMIFS(L_VALOR,L_TIPO,"Despesa",L_DATA,">="&F_INI,L_DATA,"<="&F_FIM,L_CONTA,F_CONTA,L_TIT,F_TIT,L_EXCL,"",L_CAT,A39),0) | D39: =IF(B39="Despesa",SUMIFS(L_VALOR,L_TIPO,"Despesa",L_DATA,">="&F_INI_ANT,L_DATA,"<="&F_FIM_ANT,L_CONTA,F_CONTA,L_TIT,F_TIT,L_EXCL,"",L_CAT,A39),0) | E39: =IF(C39>0.004,C39+ROW()/10^7,0) | F39: =C39-D39 | G39: =IF(F39>0.004,F39+ROW()/10^7,0)
A40: =IF(Categorias!$B$27="","",Categorias!$B$27) | B40: =IF(A40="","",Categorias!$C$27) | C40: =IF(B40="Despesa",SUMIFS(L_VALOR,L_TIPO,"Despesa",L_DATA,">="&F_INI,L_DATA,"<="&F_FIM,L_CONTA,F_CONTA,L_TIT,F_TIT,L_EXCL,"",L_CAT,A40),0) | D40: =IF(B40="Despesa",SUMIFS(L_VALOR,L_TIPO,"Despesa",L_DATA,">="&F_INI_ANT,L_DATA,"<="&F_FIM_ANT,L_CONTA,F_CONTA,L_TIT,F_TIT,L_EXCL,"",L_CAT,A40),0) | E40: =IF(C40>0.004,C40+ROW()/10^7,0) | F40: =C40-D40 | G40: =IF(F40>0.004,F40+ROW()/10^7,0)
A41: =IF(Categorias!$B$28="","",Categorias!$B$28) | B41: =IF(A41="","",Categorias!$C$28) | C41: =IF(B41="Despesa",SUMIFS(L_VALOR,L_TIPO,"Despesa",L_DATA,">="&F_INI,L_DATA,"<="&F_FIM,L_CONTA,F_CONTA,L_TIT,F_TIT,L_EXCL,"",L_CAT,A41),0) | D41: =IF(B41="Despesa",SUMIFS(L_VALOR,L_TIPO,"Despesa",L_DATA,">="&F_INI_ANT,L_DATA,"<="&F_FIM_ANT,L_CONTA,F_CONTA,L_TIT,F_TIT,L_EXCL,"",L_CAT,A41),0) | E41: =IF(C41>0.004,C41+ROW()/10^7,0) | F41: =C41-D41 | G41: =IF(F41>0.004,F41+ROW()/10^7,0)
A42: =IF(Categorias!$B$29="","",Categorias!$B$29) | B42: =IF(A42="","",Categorias!$C$29) | C42: =IF(B42="Despesa",SUMIFS(L_VALOR,L_TIPO,"Despesa",L_DATA,">="&F_INI,L_DATA,"<="&F_FIM,L_CONTA,F_CONTA,L_TIT,F_TIT,L_EXCL,"",L_CAT,A42),0) | D42: =IF(B42="Despesa",SUMIFS(L_VALOR,L_TIPO,"Despesa",L_DATA,">="&F_INI_ANT,L_DATA,"<="&F_FIM_ANT,L_CONTA,F_CONTA,L_TIT,F_TIT,L_EXCL,"",L_CAT,A42),0) | E42: =IF(C42>0.004,C42+ROW()/10^7,0) | F42: =C42-D42 | G42: =IF(F42>0.004,F42+ROW()/10^7,0)
A43: =IF(Categorias!$B$30="","",Categorias!$B$30) | B43: =IF(A43="","",Categorias!$C$30) | C43: =IF(B43="Despesa",SUMIFS(L_VALOR,L_TIPO,"Despesa",L_DATA,">="&F_INI,L_DATA,"<="&F_FIM,L_CONTA,F_CONTA,L_TIT,F_TIT,L_EXCL,"",L_CAT,A43),0) | D43: =IF(B43="Despesa",SUMIFS(L_VALOR,L_TIPO,"Despesa",L_DATA,">="&F_INI_ANT,L_DATA,"<="&F_FIM_ANT,L_CONTA,F_CONTA,L_TIT,F_TIT,L_EXCL,"",L_CAT,A43),0) | E43: =IF(C43>0.004,C43+ROW()/10^7,0) | F43: =C43-D43 | G43: =IF(F43>0.004,F43+ROW()/10^7,0)
A44: =IF(Categorias!$B$31="","",Categorias!$B$31) | B44: =IF(A44="","",Categorias!$C$31) | C44: =IF(B44="Despesa",SUMIFS(L_VALOR,L_TIPO,"Despesa",L_DATA,">="&F_INI,L_DATA,"<="&F_FIM,L_CONTA,F_CONTA,L_TIT,F_TIT,L_EXCL,"",L_CAT,A44),0) | D44: =IF(B44="Despesa",SUMIFS(L_VALOR,L_TIPO,"Despesa",L_DATA,">="&F_INI_ANT,L_DATA,"<="&F_FIM_ANT,L_CONTA,F_CONTA,L_TIT,F_TIT,L_EXCL,"",L_CAT,A44),0) | E44: =IF(C44>0.004,C44+ROW()/10^7,0) | F44: =C44-D44 | G44: =IF(F44>0.004,F44+ROW()/10^7,0)
A45: =IF(Categorias!$B$32="","",Categorias!$B$32) | B45: =IF(A45="","",Categorias!$C$32) | C45: =IF(B45="Despesa",SUMIFS(L_VALOR,L_TIPO,"Despesa",L_DATA,">="&F_INI,L_DATA,"<="&F_FIM,L_CONTA,F_CONTA,L_TIT,F_TIT,L_EXCL,"",L_CAT,A45),0) | D45: =IF(B45="Despesa",SUMIFS(L_VALOR,L_TIPO,"Despesa",L_DATA,">="&F_INI_ANT,L_DATA,"<="&F_FIM_ANT,L_CONTA,F_CONTA,L_TIT,F_TIT,L_EXCL,"",L_CAT,A45),0) | E45: =IF(C45>0.004,C45+ROW()/10^7,0) | F45: =C45-D45 | G45: =IF(F45>0.004,F45+ROW()/10^7,0)
A46: =IF(Categorias!$B$33="","",Categorias!$B$33) | B46: =IF(A46="","",Categorias!$C$33) | C46: =IF(B46="Despesa",SUMIFS(L_VALOR,L_TIPO,"Despesa",L_DATA,">="&F_INI,L_DATA,"<="&F_FIM,L_CONTA,F_CONTA,L_TIT,F_TIT,L_EXCL,"",L_CAT,A46),0) | D46: =IF(B46="Despesa",SUMIFS(L_VALOR,L_TIPO,"Despesa",L_DATA,">="&F_INI_ANT,L_DATA,"<="&F_FIM_ANT,L_CONTA,F_CONTA,L_TIT,F_TIT,L_EXCL,"",L_CAT,A46),0) | E46: =IF(C46>0.004,C46+ROW()/10^7,0) | F46: =C46-D46 | G46: =IF(F46>0.004,F46+ROW()/10^7,0)
A47: =IF(Categorias!$B$34="","",Categorias!$B$34) | B47: =IF(A47="","",Categorias!$C$34) | C47: =IF(B47="Despesa",SUMIFS(L_VALOR,L_TIPO,"Despesa",L_DATA,">="&F_INI,L_DATA,"<="&F_FIM,L_CONTA,F_CONTA,L_TIT,F_TIT,L_EXCL,"",L_CAT,A47),0) | D47: =IF(B47="Despesa",SUMIFS(L_VALOR,L_TIPO,"Despesa",L_DATA,">="&F_INI_ANT,L_DATA,"<="&F_FIM_ANT,L_CONTA,F_CONTA,L_TIT,F_TIT,L_EXCL,"",L_CAT,A47),0) | E47: =IF(C47>0.004,C47+ROW()/10^7,0) | F47: =C47-D47 | G47: =IF(F47>0.004,F47+ROW()/10^7,0)
A48: =IF(Categorias!$B$35="","",Categorias!$B$35) | B48: =IF(A48="","",Categorias!$C$35) | C48: =IF(B48="Despesa",SUMIFS(L_VALOR,L_TIPO,"Despesa",L_DATA,">="&F_INI,L_DATA,"<="&F_FIM,L_CONTA,F_CONTA,L_TIT,F_TIT,L_EXCL,"",L_CAT,A48),0) | D48: =IF(B48="Despesa",SUMIFS(L_VALOR,L_TIPO,"Despesa",L_DATA,">="&F_INI_ANT,L_DATA,"<="&F_FIM_ANT,L_CONTA,F_CONTA,L_TIT,F_TIT,L_EXCL,"",L_CAT,A48),0) | E48: =IF(C48>0.004,C48+ROW()/10^7,0) | F48: =C48-D48 | G48: =IF(F48>0.004,F48+ROW()/10^7,0)
A49: =IF(Categorias!$B$36="","",Categorias!$B$36) | B49: =IF(A49="","",Categorias!$C$36) | C49: =IF(B49="Despesa",SUMIFS(L_VALOR,L_TIPO,"Despesa",L_DATA,">="&F_INI,L_DATA,"<="&F_FIM,L_CONTA,F_CONTA,L_TIT,F_TIT,L_EXCL,"",L_CAT,A49),0) | D49: =IF(B49="Despesa",SUMIFS(L_VALOR,L_TIPO,"Despesa",L_DATA,">="&F_INI_ANT,L_DATA,"<="&F_FIM_ANT,L_CONTA,F_CONTA,L_TIT,F_TIT,L_EXCL,"",L_CAT,A49),0) | E49: =IF(C49>0.004,C49+ROW()/10^7,0) | F49: =C49-D49 | G49: =IF(F49>0.004,F49+ROW()/10^7,0)
A50: =IF(Categorias!$B$37="","",Categorias!$B$37) | B50: =IF(A50="","",Categorias!$C$37) | C50: =IF(B50="Despesa",SUMIFS(L_VALOR,L_TIPO,"Despesa",L_DATA,">="&F_INI,L_DATA,"<="&F_FIM,L_CONTA,F_CONTA,L_TIT,F_TIT,L_EXCL,"",L_CAT,A50),0) | D50: =IF(B50="Despesa",SUMIFS(L_VALOR,L_TIPO,"Despesa",L_DATA,">="&F_INI_ANT,L_DATA,"<="&F_FIM_ANT,L_CONTA,F_CONTA,L_TIT,F_TIT,L_EXCL,"",L_CAT,A50),0) | E50: =IF(C50>0.004,C50+ROW()/10^7,0) | F50: =C50-D50 | G50: =IF(F50>0.004,F50+ROW()/10^7,0)
A51: =IF(Categorias!$B$38="","",Categorias!$B$38) | B51: =IF(A51="","",Categorias!$C$38) | C51: =IF(B51="Despesa",SUMIFS(L_VALOR,L_TIPO,"Despesa",L_DATA,">="&F_INI,L_DATA,"<="&F_FIM,L_CONTA,F_CONTA,L_TIT,F_TIT,L_EXCL,"",L_CAT,A51),0) | D51: =IF(B51="Despesa",SUMIFS(L_VALOR,L_TIPO,"Despesa",L_DATA,">="&F_INI_ANT,L_DATA,"<="&F_FIM_ANT,L_CONTA,F_CONTA,L_TIT,F_TIT,L_EXCL,"",L_CAT,A51),0) | E51: =IF(C51>0.004,C51+ROW()/10^7,0) | F51: =C51-D51 | G51: =IF(F51>0.004,F51+ROW()/10^7,0)
A52: =IF(Categorias!$B$39="","",Categorias!$B$39) | B52: =IF(A52="","",Categorias!$C$39) | C52: =IF(B52="Despesa",SUMIFS(L_VALOR,L_TIPO,"Despesa",L_DATA,">="&F_INI,L_DATA,"<="&F_FIM,L_CONTA,F_CONTA,L_TIT,F_TIT,L_EXCL,"",L_CAT,A52),0) | D52: =IF(B52="Despesa",SUMIFS(L_VALOR,L_TIPO,"Despesa",L_DATA,">="&F_INI_ANT,L_DATA,"<="&F_FIM_ANT,L_CONTA,F_CONTA,L_TIT,F_TIT,L_EXCL,"",L_CAT,A52),0) | E52: =IF(C52>0.004,C52+ROW()/10^7,0) | F52: =C52-D52 | G52: =IF(F52>0.004,F52+ROW()/10^7,0)
A53: =IF(Categorias!$B$40="","",Categorias!$B$40) | B53: =IF(A53="","",Categorias!$C$40) | C53: =IF(B53="Despesa",SUMIFS(L_VALOR,L_TIPO,"Despesa",L_DATA,">="&F_INI,L_DATA,"<="&F_FIM,L_CONTA,F_CONTA,L_TIT,F_TIT,L_EXCL,"",L_CAT,A53),0) | D53: =IF(B53="Despesa",SUMIFS(L_VALOR,L_TIPO,"Despesa",L_DATA,">="&F_INI_ANT,L_DATA,"<="&F_FIM_ANT,L_CONTA,F_CONTA,L_TIT,F_TIT,L_EXCL,"",L_CAT,A53),0) | E53: =IF(C53>0.004,C53+ROW()/10^7,0) | F53: =C53-D53 | G53: =IF(F53>0.004,F53+ROW()/10^7,0)
A54: =IF(Categorias!$B$41="","",Categorias!$B$41) | B54: =IF(A54="","",Categorias!$C$41) | C54: =IF(B54="Despesa",SUMIFS(L_VALOR,L_TIPO,"Despesa",L_DATA,">="&F_INI,L_DATA,"<="&F_FIM,L_CONTA,F_CONTA,L_TIT,F_TIT,L_EXCL,"",L_CAT,A54),0) | D54: =IF(B54="Despesa",SUMIFS(L_VALOR,L_TIPO,"Despesa",L_DATA,">="&F_INI_ANT,L_DATA,"<="&F_FIM_ANT,L_CONTA,F_CONTA,L_TIT,F_TIT,L_EXCL,"",L_CAT,A54),0) | E54: =IF(C54>0.004,C54+ROW()/10^7,0) | F54: =C54-D54 | G54: =IF(F54>0.004,F54+ROW()/10^7,0)
A55: Sem categoria | B55: Despesa | C55: =MAX(0,ROUND($E$3-SUM(C15:C54),2)) | D55: =MAX(0,ROUND($E$5-SUM(D15:D54),2)) | E55: =IF(C55>0.004,C55+ROW()/10^7,0) | F55: =C55-D55 | G55: =IF(F55>0.004,F55+ROW()/10^7,0)
A59: ORÇAMENTOS (mês filtrado)
A60: categoria | B60: limite | C60: gasto | D60: pct_usado | E60: chave | I60: rank | J60: chave | K60: idx | L60: categoria | M60: limite | N60: gasto | O60: pct_usado
A61: =IF(Orçamentos!$B$2="","",Orçamentos!$B$2) | B61: =IF(A61="",0,N(Orçamentos!$C$2)) | C61: =IF(A61="",0,SUMIFS(L_VALOR,L_TIPO,"Despesa",L_DATA,">="&F_INI,L_DATA,"<="&F_FIM,L_CONTA,F_CONTA,L_TIT,F_TIT,L_EXCL,"",L_CAT,A61)) | D61: =IF(B61>0,C61/B61,0) | E61: =IF(AND(A61<>"",B61>0),D61+ROW()/10^7,0) | I61: 1 | J61: =LARGE($E$61:$E$80,I61) | K61: =IF(J61>0,MATCH(J61,$E$61:$E$80,0),0) | L61: =IF(K61>0,INDEX($A$61:$A$80,K61),"") | M61: =IF(K61>0,INDEX($B$61:$B$80,K61),0) | N61: =IF(K61>0,INDEX($C$61:$C$80,K61),0) | O61: =IF(K61>0,INDEX($D$61:$D$80,K61),0)
A62: =IF(Orçamentos!$B$3="","",Orçamentos!$B$3) | B62: =IF(A62="",0,N(Orçamentos!$C$3)) | C62: =IF(A62="",0,SUMIFS(L_VALOR,L_TIPO,"Despesa",L_DATA,">="&F_INI,L_DATA,"<="&F_FIM,L_CONTA,F_CONTA,L_TIT,F_TIT,L_EXCL,"",L_CAT,A62)) | D62: =IF(B62>0,C62/B62,0) | E62: =IF(AND(A62<>"",B62>0),D62+ROW()/10^7,0) | I62: 2 | J62: =LARGE($E$61:$E$80,I62) | K62: =IF(J62>0,MATCH(J62,$E$61:$E$80,0),0) | L62: =IF(K62>0,INDEX($A$61:$A$80,K62),"") | M62: =IF(K62>0,INDEX($B$61:$B$80,K62),0) | N62: =IF(K62>0,INDEX($C$61:$C$80,K62),0) | O62: =IF(K62>0,INDEX($D$61:$D$80,K62),0)
A63: =IF(Orçamentos!$B$4="","",Orçamentos!$B$4) | B63: =IF(A63="",0,N(Orçamentos!$C$4)) | C63: =IF(A63="",0,SUMIFS(L_VALOR,L_TIPO,"Despesa",L_DATA,">="&F_INI,L_DATA,"<="&F_FIM,L_CONTA,F_CONTA,L_TIT,F_TIT,L_EXCL,"",L_CAT,A63)) | D63: =IF(B63>0,C63/B63,0) | E63: =IF(AND(A63<>"",B63>0),D63+ROW()/10^7,0) | I63: 3 | J63: =LARGE($E$61:$E$80,I63) | K63: =IF(J63>0,MATCH(J63,$E$61:$E$80,0),0) | L63: =IF(K63>0,INDEX($A$61:$A$80,K63),"") | M63: =IF(K63>0,INDEX($B$61:$B$80,K63),0) | N63: =IF(K63>0,INDEX($C$61:$C$80,K63),0) | O63: =IF(K63>0,INDEX($D$61:$D$80,K63),0)
A64: =IF(Orçamentos!$B$5="","",Orçamentos!$B$5) | B64: =IF(A64="",0,N(Orçamentos!$C$5)) | C64: =IF(A64="",0,SUMIFS(L_VALOR,L_TIPO,"Despesa",L_DATA,">="&F_INI,L_DATA,"<="&F_FIM,L_CONTA,F_CONTA,L_TIT,F_TIT,L_EXCL,"",L_CAT,A64)) | D64: =IF(B64>0,C64/B64,0) | E64: =IF(AND(A64<>"",B64>0),D64+ROW()/10^7,0) | I64: 4 | J64: =LARGE($E$61:$E$80,I64) | K64: =IF(J64>0,MATCH(J64,$E$61:$E$80,0),0) | L64: =IF(K64>0,INDEX($A$61:$A$80,K64),"") | M64: =IF(K64>0,INDEX($B$61:$B$80,K64),0) | N64: =IF(K64>0,INDEX($C$61:$C$80,K64),0) | O64: =IF(K64>0,INDEX($D$61:$D$80,K64),0)
A65: =IF(Orçamentos!$B$6="","",Orçamentos!$B$6) | B65: =IF(A65="",0,N(Orçamentos!$C$6)) | C65: =IF(A65="",0,SUMIFS(L_VALOR,L_TIPO,"Despesa",L_DATA,">="&F_INI,L_DATA,"<="&F_FIM,L_CONTA,F_CONTA,L_TIT,F_TIT,L_EXCL,"",L_CAT,A65)) | D65: =IF(B65>0,C65/B65,0) | E65: =IF(AND(A65<>"",B65>0),D65+ROW()/10^7,0) | I65: 5 | J65: =LARGE($E$61:$E$80,I65) | K65: =IF(J65>0,MATCH(J65,$E$61:$E$80,0),0) | L65: =IF(K65>0,INDEX($A$61:$A$80,K65),"") | M65: =IF(K65>0,INDEX($B$61:$B$80,K65),0) | N65: =IF(K65>0,INDEX($C$61:$C$80,K65),0) | O65: =IF(K65>0,INDEX($D$61:$D$80,K65),0)
A66: =IF(Orçamentos!$B$7="","",Orçamentos!$B$7) | B66: =IF(A66="",0,N(Orçamentos!$C$7)) | C66: =IF(A66="",0,SUMIFS(L_VALOR,L_TIPO,"Despesa",L_DATA,">="&F_INI,L_DATA,"<="&F_FIM,L_CONTA,F_CONTA,L_TIT,F_TIT,L_EXCL,"",L_CAT,A66)) | D66: =IF(B66>0,C66/B66,0) | E66: =IF(AND(A66<>"",B66>0),D66+ROW()/10^7,0) | I66: 6 | J66: =LARGE($E$61:$E$80,I66) | K66: =IF(J66>0,MATCH(J66,$E$61:$E$80,0),0) | L66: =IF(K66>0,INDEX($A$61:$A$80,K66),"") | M66: =IF(K66>0,INDEX($B$61:$B$80,K66),0) | N66: =IF(K66>0,INDEX($C$61:$C$80,K66),0) | O66: =IF(K66>0,INDEX($D$61:$D$80,K66),0)
A67: =IF(Orçamentos!$B$8="","",Orçamentos!$B$8) | B67: =IF(A67="",0,N(Orçamentos!$C$8)) | C67: =IF(A67="",0,SUMIFS(L_VALOR,L_TIPO,"Despesa",L_DATA,">="&F_INI,L_DATA,"<="&F_FIM,L_CONTA,F_CONTA,L_TIT,F_TIT,L_EXCL,"",L_CAT,A67)) | D67: =IF(B67>0,C67/B67,0) | E67: =IF(AND(A67<>"",B67>0),D67+ROW()/10^7,0) | I67: 7 | J67: =LARGE($E$61:$E$80,I67) | K67: =IF(J67>0,MATCH(J67,$E$61:$E$80,0),0) | L67: =IF(K67>0,INDEX($A$61:$A$80,K67),"") | M67: =IF(K67>0,INDEX($B$61:$B$80,K67),0) | N67: =IF(K67>0,INDEX($C$61:$C$80,K67),0) | O67: =IF(K67>0,INDEX($D$61:$D$80,K67),0)
A68: =IF(Orçamentos!$B$9="","",Orçamentos!$B$9) | B68: =IF(A68="",0,N(Orçamentos!$C$9)) | C68: =IF(A68="",0,SUMIFS(L_VALOR,L_TIPO,"Despesa",L_DATA,">="&F_INI,L_DATA,"<="&F_FIM,L_CONTA,F_CONTA,L_TIT,F_TIT,L_EXCL,"",L_CAT,A68)) | D68: =IF(B68>0,C68/B68,0) | E68: =IF(AND(A68<>"",B68>0),D68+ROW()/10^7,0) | I68: 8 | J68: =LARGE($E$61:$E$80,I68) | K68: =IF(J68>0,MATCH(J68,$E$61:$E$80,0),0) | L68: =IF(K68>0,INDEX($A$61:$A$80,K68),"") | M68: =IF(K68>0,INDEX($B$61:$B$80,K68),0) | N68: =IF(K68>0,INDEX($C$61:$C$80,K68),0) | O68: =IF(K68>0,INDEX($D$61:$D$80,K68),0)
A69: =IF(Orçamentos!$B$10="","",Orçamentos!$B$10) | B69: =IF(A69="",0,N(Orçamentos!$C$10)) | C69: =IF(A69="",0,SUMIFS(L_VALOR,L_TIPO,"Despesa",L_DATA,">="&F_INI,L_DATA,"<="&F_FIM,L_CONTA,F_CONTA,L_TIT,F_TIT,L_EXCL,"",L_CAT,A69)) | D69: =IF(B69>0,C69/B69,0) | E69: =IF(AND(A69<>"",B69>0),D69+ROW()/10^7,0)
A70: =IF(Orçamentos!$B$11="","",Orçamentos!$B$11) | B70: =IF(A70="",0,N(Orçamentos!$C$11)) | C70: =IF(A70="",0,SUMIFS(L_VALOR,L_TIPO,"Despesa",L_DATA,">="&F_INI,L_DATA,"<="&F_FIM,L_CONTA,F_CONTA,L_TIT,F_TIT,L_EXCL,"",L_CAT,A70)) | D70: =IF(B70>0,C70/B70,0) | E70: =IF(AND(A70<>"",B70>0),D70+ROW()/10^7,0)
A71: =IF(Orçamentos!$B$12="","",Orçamentos!$B$12) | B71: =IF(A71="",0,N(Orçamentos!$C$12)) | C71: =IF(A71="",0,SUMIFS(L_VALOR,L_TIPO,"Despesa",L_DATA,">="&F_INI,L_DATA,"<="&F_FIM,L_CONTA,F_CONTA,L_TIT,F_TIT,L_EXCL,"",L_CAT,A71)) | D71: =IF(B71>0,C71/B71,0) | E71: =IF(AND(A71<>"",B71>0),D71+ROW()/10^7,0)
A72: =IF(Orçamentos!$B$13="","",Orçamentos!$B$13) | B72: =IF(A72="",0,N(Orçamentos!$C$13)) | C72: =IF(A72="",0,SUMIFS(L_VALOR,L_TIPO,"Despesa",L_DATA,">="&F_INI,L_DATA,"<="&F_FIM,L_CONTA,F_CONTA,L_TIT,F_TIT,L_EXCL,"",L_CAT,A72)) | D72: =IF(B72>0,C72/B72,0) | E72: =IF(AND(A72<>"",B72>0),D72+ROW()/10^7,0)
A73: =IF(Orçamentos!$B$14="","",Orçamentos!$B$14) | B73: =IF(A73="",0,N(Orçamentos!$C$14)) | C73: =IF(A73="",0,SUMIFS(L_VALOR,L_TIPO,"Despesa",L_DATA,">="&F_INI,L_DATA,"<="&F_FIM,L_CONTA,F_CONTA,L_TIT,F_TIT,L_EXCL,"",L_CAT,A73)) | D73: =IF(B73>0,C73/B73,0) | E73: =IF(AND(A73<>"",B73>0),D73+ROW()/10^7,0)
A74: =IF(Orçamentos!$B$15="","",Orçamentos!$B$15) | B74: =IF(A74="",0,N(Orçamentos!$C$15)) | C74: =IF(A74="",0,SUMIFS(L_VALOR,L_TIPO,"Despesa",L_DATA,">="&F_INI,L_DATA,"<="&F_FIM,L_CONTA,F_CONTA,L_TIT,F_TIT,L_EXCL,"",L_CAT,A74)) | D74: =IF(B74>0,C74/B74,0) | E74: =IF(AND(A74<>"",B74>0),D74+ROW()/10^7,0)
A75: =IF(Orçamentos!$B$16="","",Orçamentos!$B$16) | B75: =IF(A75="",0,N(Orçamentos!$C$16)) | C75: =IF(A75="",0,SUMIFS(L_VALOR,L_TIPO,"Despesa",L_DATA,">="&F_INI,L_DATA,"<="&F_FIM,L_CONTA,F_CONTA,L_TIT,F_TIT,L_EXCL,"",L_CAT,A75)) | D75: =IF(B75>0,C75/B75,0) | E75: =IF(AND(A75<>"",B75>0),D75+ROW()/10^7,0)
A76: =IF(Orçamentos!$B$17="","",Orçamentos!$B$17) | B76: =IF(A76="",0,N(Orçamentos!$C$17)) | C76: =IF(A76="",0,SUMIFS(L_VALOR,L_TIPO,"Despesa",L_DATA,">="&F_INI,L_DATA,"<="&F_FIM,L_CONTA,F_CONTA,L_TIT,F_TIT,L_EXCL,"",L_CAT,A76)) | D76: =IF(B76>0,C76/B76,0) | E76: =IF(AND(A76<>"",B76>0),D76+ROW()/10^7,0)
A77: =IF(Orçamentos!$B$18="","",Orçamentos!$B$18) | B77: =IF(A77="",0,N(Orçamentos!$C$18)) | C77: =IF(A77="",0,SUMIFS(L_VALOR,L_TIPO,"Despesa",L_DATA,">="&F_INI,L_DATA,"<="&F_FIM,L_CONTA,F_CONTA,L_TIT,F_TIT,L_EXCL,"",L_CAT,A77)) | D77: =IF(B77>0,C77/B77,0) | E77: =IF(AND(A77<>"",B77>0),D77+ROW()/10^7,0)
A78: =IF(Orçamentos!$B$19="","",Orçamentos!$B$19) | B78: =IF(A78="",0,N(Orçamentos!$C$19)) | C78: =IF(A78="",0,SUMIFS(L_VALOR,L_TIPO,"Despesa",L_DATA,">="&F_INI,L_DATA,"<="&F_FIM,L_CONTA,F_CONTA,L_TIT,F_TIT,L_EXCL,"",L_CAT,A78)) | D78: =IF(B78>0,C78/B78,0) | E78: =IF(AND(A78<>"",B78>0),D78+ROW()/10^7,0)
A79: =IF(Orçamentos!$B$20="","",Orçamentos!$B$20) | B79: =IF(A79="",0,N(Orçamentos!$C$20)) | C79: =IF(A79="",0,SUMIFS(L_VALOR,L_TIPO,"Despesa",L_DATA,">="&F_INI,L_DATA,"<="&F_FIM,L_CONTA,F_CONTA,L_TIT,F_TIT,L_EXCL,"",L_CAT,A79)) | D79: =IF(B79>0,C79/B79,0) | E79: =IF(AND(A79<>"",B79>0),D79+ROW()/10^7,0)
A80: =IF(Orçamentos!$B$21="","",Orçamentos!$B$21) | B80: =IF(A80="",0,N(Orçamentos!$C$21)) | C80: =IF(A80="",0,SUMIFS(L_VALOR,L_TIPO,"Despesa",L_DATA,">="&F_INI,L_DATA,"<="&F_FIM,L_CONTA,F_CONTA,L_TIT,F_TIT,L_EXCL,"",L_CAT,A80)) | D80: =IF(B80>0,C80/B80,0) | E80: =IF(AND(A80<>"",B80>0),D80+ROW()/10^7,0)
A84: mes | B84: rotulo | C84: Receitas | D84: Despesas
A85: =EDATE(F_INI,-5) | B85: =INDEX('_Listas'!$C$2:$C$13,MONTH(A85))&"/"&RIGHT(YEAR(A85),2) | C85: =SUMIFS(L_VALOR,L_TIPO,"Receita",L_DATA,">="&A85,L_DATA,"<="&EOMONTH(A85,0),L_CONTA,F_CONTA,L_TIT,F_TIT,L_EXCL,"") | D85: =SUMIFS(L_VALOR,L_TIPO,"Despesa",L_DATA,">="&A85,L_DATA,"<="&EOMONTH(A85,0),L_CONTA,F_CONTA,L_TIT,F_TIT,L_EXCL,"")
A86: =EDATE(F_INI,-4) | B86: =INDEX('_Listas'!$C$2:$C$13,MONTH(A86))&"/"&RIGHT(YEAR(A86),2) | C86: =SUMIFS(L_VALOR,L_TIPO,"Receita",L_DATA,">="&A86,L_DATA,"<="&EOMONTH(A86,0),L_CONTA,F_CONTA,L_TIT,F_TIT,L_EXCL,"") | D86: =SUMIFS(L_VALOR,L_TIPO,"Despesa",L_DATA,">="&A86,L_DATA,"<="&EOMONTH(A86,0),L_CONTA,F_CONTA,L_TIT,F_TIT,L_EXCL,"")
A87: =EDATE(F_INI,-3) | B87: =INDEX('_Listas'!$C$2:$C$13,MONTH(A87))&"/"&RIGHT(YEAR(A87),2) | C87: =SUMIFS(L_VALOR,L_TIPO,"Receita",L_DATA,">="&A87,L_DATA,"<="&EOMONTH(A87,0),L_CONTA,F_CONTA,L_TIT,F_TIT,L_EXCL,"") | D87: =SUMIFS(L_VALOR,L_TIPO,"Despesa",L_DATA,">="&A87,L_DATA,"<="&EOMONTH(A87,0),L_CONTA,F_CONTA,L_TIT,F_TIT,L_EXCL,"")
A88: =EDATE(F_INI,-2) | B88: =INDEX('_Listas'!$C$2:$C$13,MONTH(A88))&"/"&RIGHT(YEAR(A88),2) | C88: =SUMIFS(L_VALOR,L_TIPO,"Receita",L_DATA,">="&A88,L_DATA,"<="&EOMONTH(A88,0),L_CONTA,F_CONTA,L_TIT,F_TIT,L_EXCL,"") | D88: =SUMIFS(L_VALOR,L_TIPO,"Despesa",L_DATA,">="&A88,L_DATA,"<="&EOMONTH(A88,0),L_CONTA,F_CONTA,L_TIT,F_TIT,L_EXCL,"")
A89: =EDATE(F_INI,-1) | B89: =INDEX('_Listas'!$C$2:$C$13,MONTH(A89))&"/"&RIGHT(YEAR(A89),2) | C89: =SUMIFS(L_VALOR,L_TIPO,"Receita",L_DATA,">="&A89,L_DATA,"<="&EOMONTH(A89,0),L_CONTA,F_CONTA,L_TIT,F_TIT,L_EXCL,"") | D89: =SUMIFS(L_VALOR,L_TIPO,"Despesa",L_DATA,">="&A89,L_DATA,"<="&EOMONTH(A89,0),L_CONTA,F_CONTA,L_TIT,F_TIT,L_EXCL,"")
A90: =EDATE(F_INI,0) | B90: =INDEX('_Listas'!$C$2:$C$13,MONTH(A90))&"/"&RIGHT(YEAR(A90),2) | C90: =SUMIFS(L_VALOR,L_TIPO,"Receita",L_DATA,">="&A90,L_DATA,"<="&EOMONTH(A90,0),L_CONTA,F_CONTA,L_TIT,F_TIT,L_EXCL,"") | D90: =SUMIFS(L_VALOR,L_TIPO,"Despesa",L_DATA,">="&A90,L_DATA,"<="&EOMONTH(A90,0),L_CONTA,F_CONTA,L_TIT,F_TIT,L_EXCL,"")
A94: GASTOS POR DIA
A95: dia | B95: Despesas
A96: 1 | B96: =IF(A96>DAY(F_FIM),0,SUMIFS(L_VALOR,L_TIPO,"Despesa",L_DATA,F_INI+A96-1,L_CONTA,F_CONTA,L_TIT,F_TIT,L_EXCL,""))
A97: 2 | B97: =IF(A97>DAY(F_FIM),0,SUMIFS(L_VALOR,L_TIPO,"Despesa",L_DATA,F_INI+A97-1,L_CONTA,F_CONTA,L_TIT,F_TIT,L_EXCL,""))
A98: 3 | B98: =IF(A98>DAY(F_FIM),0,SUMIFS(L_VALOR,L_TIPO,"Despesa",L_DATA,F_INI+A98-1,L_CONTA,F_CONTA,L_TIT,F_TIT,L_EXCL,""))
A99: 4 | B99: =IF(A99>DAY(F_FIM),0,SUMIFS(L_VALOR,L_TIPO,"Despesa",L_DATA,F_INI+A99-1,L_CONTA,F_CONTA,L_TIT,F_TIT,L_EXCL,""))
A100: 5 | B100: =IF(A100>DAY(F_FIM),0,SUMIFS(L_VALOR,L_TIPO,"Despesa",L_DATA,F_INI+A100-1,L_CONTA,F_CONTA,L_TIT,F_TIT,L_EXCL,""))
A101: 6 | B101: =IF(A101>DAY(F_FIM),0,SUMIFS(L_VALOR,L_TIPO,"Despesa",L_DATA,F_INI+A101-1,L_CONTA,F_CONTA,L_TIT,F_TIT,L_EXCL,""))
A102: 7 | B102: =IF(A102>DAY(F_FIM),0,SUMIFS(L_VALOR,L_TIPO,"Despesa",L_DATA,F_INI+A102-1,L_CONTA,F_CONTA,L_TIT,F_TIT,L_EXCL,""))
A103: 8 | B103: =IF(A103>DAY(F_FIM),0,SUMIFS(L_VALOR,L_TIPO,"Despesa",L_DATA,F_INI+A103-1,L_CONTA,F_CONTA,L_TIT,F_TIT,L_EXCL,""))
A104: 9 | B104: =IF(A104>DAY(F_FIM),0,SUMIFS(L_VALOR,L_TIPO,"Despesa",L_DATA,F_INI+A104-1,L_CONTA,F_CONTA,L_TIT,F_TIT,L_EXCL,""))
A105: 10 | B105: =IF(A105>DAY(F_FIM),0,SUMIFS(L_VALOR,L_TIPO,"Despesa",L_DATA,F_INI+A105-1,L_CONTA,F_CONTA,L_TIT,F_TIT,L_EXCL,""))
A106: 11 | B106: =IF(A106>DAY(F_FIM),0,SUMIFS(L_VALOR,L_TIPO,"Despesa",L_DATA,F_INI+A106-1,L_CONTA,F_CONTA,L_TIT,F_TIT,L_EXCL,""))
A107: 12 | B107: =IF(A107>DAY(F_FIM),0,SUMIFS(L_VALOR,L_TIPO,"Despesa",L_DATA,F_INI+A107-1,L_CONTA,F_CONTA,L_TIT,F_TIT,L_EXCL,""))
... A126: 31 | B126: =IF(A126>DAY(F_FIM),0,SUMIFS(L_VALOR,L_TIPO,"Despesa",L_DATA,F_INI+A126-1,L_CONTA,F_CONTA,L_TIT,F_TIT,L_EXCL,""))
A129: MAIORES DESPESAS DO MÊS
...
